src/definitions.sv
`ifndef DEFINITIONS_SV
`define DEFINITIONS_SV

// ALU control signals
`define ALU_ADD 3'b000
`define ALU_SUB 3'b001
`define ALU_AND 3'b010
`define ALU_OR  3'b011

// Opcode definitions (no JAL, only these 4 types)
`define OP_R_TYPE   7'b0110011  // ADD, SUB, AND, OR
`define OP_I_TYPE   7'b0000011  // LD  (Load Double)
`define OP_S_TYPE   7'b0100011  // SD  (Store Double)
`define OP_B_TYPE   7'b1100011  // BEQ (Branch if Equal) 

// Function codes for R‑type
`define FUNC3_ADD_SUB 3'b000
`define FUNC3_AND     3'b111
`define FUNC3_OR      3'b110

`define FUNC7_ADD     7'b0000000
`define FUNC7_SUB     7'b0100000

`endif

src/alu.sv
`include "definitions.sv"

module alu (
    input  logic [63:0] a,
    input  logic [63:0] b,
    input  logic [2:0]  alu_control,
    output logic [63:0] result,
    output logic        zero
);

    always_comb begin
        case (alu_control)
            `ALU_ADD: result = a + b;
            `ALU_SUB: result = a - b;
            `ALU_AND: result = a & b;
            `ALU_OR:  result = a | b;
            default:  result = a + b;
        endcase
    end

    assign zero = (result == 64'b0);

endmodule

reg_file_gaurav.sv
module reg_file(
    input logic clk,
    input logic rst,
    input logic[4:0] rd_addr1,
    output logic[63:0] rd_data1,
    input logic[4:0] rd_addr2,
    output logic[63:0] rd_data2,
    input logic[4:0] wr_addr,
    input logic[63:0] wr_data,
    input logic wr_enable,

    output logic[63:0] debug_output //reg 31 which is connected to output pins
);
logic [63:0] registers[31:0];

always_ff@(posedge clk or posedge rst) begin
    if(rst) begin
        for(int i=0;i<32;i++) begin
            registers[i]<=64'b0;
        end
    end
    else if(wr_enable) begin
        registers[wr_addr]<=wr_data;
    end
end

assign rd_data1=registers[rd_addr1];
assign rd_data2=registers[rd_addr2];

assign debug_output=registers[31];

endmodule

src/data_path.sv
module datapath (
    input  logic        clk,
    input  logic        rst,
    input  logic [31:0] instruction,
    input  logic [63:0] read_data_memory,
    input  logic [2:0]  alu_control,
    input  logic        reg_write,
    input  logic        alu_src,
    input  logic        mem_to_reg,

    output logic [63:0] alu_result,
    output logic [63:0] write_data_memory,
    output logic [4:0]  rd_addr,
    output logic        zero,
    output logic [63:0] debug_out  // (optional) contents of x31
);

    // Register‑file wires
    logic [63:0] rs1_data, rs2_data;
    logic [63:0] imm;
    logic [63:0] alu_b;
    logic [63:0] wb_data;

    // Decode register indices
    logic [4:0] rs1 = instruction[19:15]; 
    logic [4:0] rs2 = instruction[24:20];
    assign rd_addr = instruction[11:7];

    // Instantiate register file
    reg_file rf (
        .clk        (clk),
        .rst        (rst),
        .rd_addr1   (rs1),
        .rd_data1   (rs1_data),
        .rd_addr2   (rs2),
        .rd_data2   (rs2_data),
        .wr_addr    (rd_addr),
        .wr_data    (wb_data),
        .wr_enable  (reg_write),
        .debug_output(debug_out)
    );

    // Sign‑extended immediate (LD / BEQ)
    assign imm   = {{52{instruction[31]}}, instruction[31:20]};

    // ALU input mux: either register or immediate
    assign alu_b = (alu_src) ? imm : rs2_data;

    // Launch ALU
    alu alu_inst (
        .a           (rs1_data),
        .b           (alu_b),
        .alu_control (alu_control),
        .result      (alu_result),
        .zero        (zero)
    );

    // Data memory will write rs2_data
    assign write_data_memory = rs2_data;

    // Write‑back mux: from memory or from ALU
    assign wb_data = (mem_to_reg) ? read_data_memory : alu_result;

endmodule

src/data_mem.sv
module data_mem #(
    parameter integer mem_size = 256,
    parameter integer rom_size = 8,
    parameter string  rom_file = "programs/fibo_data.mem"
) (
    input  logic        clk,
    input  logic        rst,
    input  logic [31:0] addr,
    input  logic [63:0] wr_data,
    input  logic        wr_enable,
    input  logic        rd_enable,
    output logic [63:0] rd_data
);

    // Memory array
    reg [63:0] memory_array [0:mem_size-1];
    
    // Word address
    wire [31:0] word_addr = addr[31:3];

    // Initialize memory
    integer i;
    initial begin
        // Initialize all memory to zero
        for (i = 0; i < mem_size; i = i + 1) begin
            memory_array[i] = 64'b0;
        end
        
        // Load ROM data from file
        $display("Loading data memory from %s", rom_file);
        $readmemh(rom_file, memory_array, 0, rom_size-1);
        
        // Display loaded data
        $display("Loaded data memory:");
        for (i = 0; i < rom_size; i = i + 1) begin
            $display("  [%0d]: 0x%h (%0d)", i, memory_array[i], memory_array[i]);
        end
    end

    // Write operation
    always_ff @(posedge clk) begin
        if (wr_enable && word_addr >= rom_size && word_addr < mem_size) begin
            memory_array[word_addr] <= wr_data;
            $display("MEM WRITE: addr=%0d, data=%0d", word_addr, wr_data);
        end else if (wr_enable && word_addr < rom_size) begin
            $display("WARNING: Attempted write to ROM region at address %0d", word_addr);
        end
    end

    // Read operation - always output data
    assign rd_data = (word_addr < mem_size) ? memory_array[word_addr] : 64'b0;

endmodule

src/control_unit.sv
// File: src/control_unit.sv
`include "definitions.sv"

module control_unit (
    input  logic [6:0] opcode,
    input  logic [2:0] funct3,
    input  logic [6:0] funct7,
    output logic [2:0] alu_control,   // ALU operation select
    output logic       reg_write,     // Write to register file?
    output logic       mem_read,      // Read from data_mem?
    output logic       mem_write,     // Write to data_mem?
    output logic       mem_to_reg,    // Write-back: memory or ALU?
    output logic       alu_src,       // ALU second input = immediate?
    output logic       branch         // BEQ?
);

    always_comb begin
        // Defaults
        alu_control = `ALU_ADD;
        reg_write   = 1'b0;
        mem_read    = 1'b0;
        mem_write   = 1'b0;
        mem_to_reg  = 1'b0;
        alu_src     = 1'b0;
        branch      = 1'b0;

        // If opcode is all X's (unknown), do nothing
        if (opcode === 7'bxxxxxxx) begin
            // keep defaults; no warning
        end else begin
            case (opcode)
                // I-Type (LD)
                `OP_I_TYPE: begin
                    alu_control = `ALU_ADD;
                    reg_write   = 1'b1;
                    mem_read    = 1'b1;
                    mem_write   = 1'b0;
                    mem_to_reg  = 1'b1;
                    alu_src     = 1'b1;
                    branch      = 1'b0;
                end

                // I-Type ALU operations (ADDI, etc.)
                `OP_I_ALU: begin
                    alu_control = `ALU_ADD;
                    reg_write   = 1'b1;
                    mem_read    = 1'b0;
                    mem_write   = 1'b0;
                    mem_to_reg  = 1'b0;
                    alu_src     = 1'b1;  // Use immediate
                    branch      = 1'b0;
                end

                // S-Type (SD)
                `OP_S_TYPE: begin
                    alu_control = `ALU_ADD;
                    reg_write   = 1'b0;
                    mem_read    = 1'b0;
                    mem_write   = 1'b1;
                    mem_to_reg  = 1'b0;
                    alu_src     = 1'b1;
                    branch      = 1'b0;
                end

                // R-Type (ADD/SUB/AND/OR)
                `OP_R_TYPE: begin
                    case (funct3)
                        `FUNC3_ADD_SUB: begin
                            if (funct7 == `FUNC7_SUB)
                                alu_control = `ALU_SUB;
                            else
                                alu_control = `ALU_ADD;
                        end
                        `FUNC3_AND: alu_control = `ALU_AND;
                        `FUNC3_OR:  alu_control = `ALU_OR;
                        default:    alu_control = `ALU_ADD;
                    endcase
                    
                    reg_write   = 1'b1;
                    mem_read    = 1'b0;
                    mem_write   = 1'b0;
                    mem_to_reg  = 1'b0;
                    alu_src     = 1'b0;
                    branch      = 1'b0;
                end

                // B-Type (BEQ)
                `OP_B_TYPE: begin
                    alu_control = `ALU_SUB;  // Subtract to compare
                    reg_write   = 1'b0;      // Don't write to register
                    mem_read    = 1'b0;      // Don't access memory
                    mem_write   = 1'b0;      // Don't access memory
                    mem_to_reg  = 1'b0;      // Don't care
                    alu_src     = 1'b0;      // Use register for comparison
                    branch      = 1'b1;      // This is a branch instruction
                end

                default: begin
                    $display("Warning: Unknown opcode: 0x%h", opcode);
                end
            endcase
        end
    end

endmodule

src/sign_extend.sv
`include "definitions.sv"

module sign_extend (
    input  logic [31:0] instr,
    output logic [63:0] imm_out
);

    // Different immediate formats
    logic [63:0] imm_i, imm_s, imm_b;
    
    // I-type immediate (bits [31:20]) - for LD and ADDI
    assign imm_i = {{52{instr[31]}}, instr[31:20]};
    
    // S-type immediate (bits [31:25] + [11:7]) - for SD
    assign imm_s = {{52{instr[31]}}, instr[31:25], instr[11:7]};
    
    // B-type immediate (bits: [31], [7], [30:25], [11:8], then <<1) - for BEQ
    assign imm_b = {{51{instr[31]}}, instr[31], instr[7], instr[30:25], instr[11:8], 1'b0};

    // Fixed version - replace always_comb with direct assignments to avoid the warning
    assign imm_out = (instr[6:0] == `OP_S_TYPE) ? imm_s :
                     (instr[6:0] == `OP_B_TYPE) ? imm_b : imm_i;

endmodule

src/instr_mem.sv
module instr_mem #(
    parameter integer mem_size = 17,  // Increased from 10 to 20
    parameter string  mem_file = "programs/program.mem"
) (
    input  logic [31:0] address,
    output logic [31:0] instruction
);

    // Instruction array
    reg [31:0] memory_array [0:mem_size-1];
    
    // Initialize with NOP instructions first
    integer i;
    initial begin
        // Initialize all to NOP
        for (i = 0; i < mem_size; i = i + 1) begin
            memory_array[i] = 32'h00000013;  // NOP (addi x0, x0, 0)
        end
        
        // Load instructions from file
        $display("Loading instruction memory from %s", mem_file);
        $readmemh(mem_file, memory_array);
        
        // Display loaded instructions
        $display("Loaded instructions:");
        for (i = 0; i < mem_size && i < 20; i = i + 1) begin
            if (memory_array[i] != 32'h00000013) begin
                $display("  [%0d]: 0x%h", i, memory_array[i]);
            end
        end
    end

    // Output instruction
    wire [31:0] word_addr = address[31:2];
    assign instruction = (word_addr < mem_size) ? memory_array[word_addr] : 32'h00000013;

endmodule

src/pc_logic.sv
module pc_logic (
    input  logic        clk,
    input  logic        rst,
    input  logic        branch,
    input  logic        zero,
    input  logic [63:0] imm,
    output logic [63:0] pc
);

    logic [63:0] pc_next;
    logic        take_branch;
    
    // Branch decision: take branch if it's a branch instruction AND zero flag is set
    assign take_branch = branch & zero;
    
    // Next PC calculation
    always_comb begin
        if (take_branch) begin
            // Branch taken: PC = PC + sign_extended_offset
            pc_next = pc + imm;
        end else begin
            // Normal increment: PC = PC + 4
            pc_next = pc + 64'd4;
        end
    end

    // PC register
    always_ff @(posedge clk or posedge rst) begin
        if (rst) begin
            pc <= 64'b0;
        end else begin
            pc <= pc_next;
        end
    end

endmodule

src/single_cycle_cpu.sv
`include "definitions.sv"

module single_cycle_cpu (
    input  logic        clk,
    input  logic        rst,
    output logic [63:0] debug_out
);

    // Internal signals
    logic [63:0] pc;
    logic [31:0] instruction;
    logic [63:0] imm;

    // Control signals
    logic [2:0]  alu_control;
    logic        reg_write;
    logic        mem_read;
    logic        mem_write;
    logic        mem_to_reg;
    logic        alu_src;
    logic        branch;

    // Datapath signals
    logic [63:0] alu_result;
    logic [63:0] write_data_memory;
    logic [63:0] read_data_memory;
    logic [4:0]  rd_addr;
    logic        zero;

    // Program Counter
    pc_logic pc_inst (
        .clk    (clk),
        .rst    (rst),
        .branch (branch),
        .zero   (zero),
        .imm    (imm),
        .pc     (pc)
    );

    // Instruction Memory - now loads from file
    instr_mem #(
        .mem_size(17),
        .mem_file("programs/fibo_comp.mem")
    ) instr_mem_inst (
        .address    (pc[31:0]),
        .instruction(instruction)
    );

    // Sign Extension
    sign_extend sign_ext_inst (
        .instr   (instruction),
        .imm_out (imm)
    );

    // Control Unit
    control_unit cu_inst (
        .opcode      (instruction[6:0]),
        .funct3      (instruction[14:12]),
        .funct7      (instruction[31:25]),
        .alu_control (alu_control),
        .reg_write   (reg_write),
        .mem_read    (mem_read),
        .mem_write   (mem_write),
        .mem_to_reg  (mem_to_reg),
        .alu_src     (alu_src),
        .branch      (branch)
    );

    // Data Memory - now loads from file
    data_mem #(
        .mem_size(256),
        .rom_size(2),
        .rom_file("programs/fibo_data.mem")
    ) data_mem_inst (
        .clk       (clk),
        .rst       (rst),
        .addr      (alu_result[31:0]),
        .wr_data   (write_data_memory),
        .wr_enable (mem_write),
        .rd_enable (1'b1),
        .rd_data   (read_data_memory)
    );

    // Datapath
    datapath dp_inst (
        .clk                 (clk),
        .rst                 (rst),
        .instruction         (instruction),
        .read_data_memory    (read_data_memory),
        .alu_control         (alu_control),
        .reg_write           (reg_write),
        .alu_src             (alu_src),
        .mem_to_reg          (mem_to_reg),
        .alu_result          (alu_result),
        .write_data_memory   (write_data_memory),
        .rd_addr             (rd_addr),
        .zero                (zero),
        .debug_out           (debug_out)
    );

endmodule

testbench/fibo_tb.sv
`timescale 1ns/1ps

module tb_fibonacci_comprehensive;
    // Clock, reset, debug output
    logic        clk, rst;
    logic [63:0] debug_out;

    // Instruction counters
    int load_count   = 0;
    int store_count  = 0;
    int add_count    = 0;
    int sub_count    = 0;
    int and_count    = 0;
    int or_count     = 0;
    int beq_count    = 0;
    int addi_count   = 0;
    int total_instr  = 0;
    int cycle_count  = 0;

    // Expected Fibonacci values (initialized later)
    static logic [63:0] expected_fib [0:9];

    // Workspace variables
    logic [63:0] fib_value;
    int correct_count;

    // Instantiate CPU with Fibonacci program
    single_cycle_cpu uut (
        .clk      (clk),
        .rst      (rst),
        .debug_out(debug_out)
    );

    // Override memory files for this test
    defparam uut.instr_mem_inst.mem_size  = 17;
    defparam uut.instr_mem_inst.mem_file  = "programs/fibo_comp.mem";
    defparam uut.data_mem_inst.rom_file   = "programs/fibo_data.mem";
    defparam uut.data_mem_inst.rom_size   = 2;

    // Clock generation
    initial clk = 0;
    always #5 clk = ~clk;

    // Main test sequence
    initial begin
        $dumpfile("fibo_comp.vcd");
        $dumpvars(0, tb_fibonacci_comprehensive);

        // Initialize expected_fib array
        expected_fib[0] = 1;
        expected_fib[1] = 1;
        expected_fib[2] = 2;
        expected_fib[3] = 3;
        expected_fib[4] = 5;
        expected_fib[5] = 8;
        expected_fib[6] = 13;
        expected_fib[7] = 21;
        expected_fib[8] = 34;
        expected_fib[9] = 55;

        // Display header
        $display("=== RISC-V Fibonacci Comprehensive Test ===");
        $display("Testing ALL instructions with Fibonacci sequence calculation\n");

        // Reset
        rst = 1;
        #20;
        rst = 0;
        $display("Reset released, starting Fibonacci calculation...\n");

        // Run simulation
        #1000;

        // Report final register values
        $display("=== FINAL RESULTS ===");
        $display("Debug output (Register 31): %0d", debug_out);
        $display("Register 1 (Fib n-1): %0d", uut.dp_inst.rf.registers[1]);
        $display("Register 2 (Fib n):   %0d", uut.dp_inst.rf.registers[2]);
        $display("Register 3 (Fib n+1): %0d", uut.dp_inst.rf.registers[3]);
        $display("Register 5 (index):   %0d\n", uut.dp_inst.rf.registers[5]);

        // Instruction coverage
        $display("=== INSTRUCTION COVERAGE ===");
        $display("Total instructions: %0d", total_instr);
        $display(" LD:   %0d", load_count);
        $display(" SD:   %0d", store_count);
        $display(" ADD:  %0d", add_count);
        $display(" SUB:  %0d", sub_count);
        $display(" AND:  %0d", and_count);
        $display(" OR:   %0d", or_count);
        $display(" BEQ:  %0d", beq_count);
        $display(" ADDI: %0d\n", addi_count);

        if (load_count>0 && store_count>0 && add_count>0 && sub_count>0 &&
            and_count>0 && or_count>0 && beq_count>0 && addi_count>0) begin
            $display("✓ SUCCESS: All instruction types executed!\n");
        end else begin
            $display("✗ FAILURE: Missing instruction executions!\n");
        end

        // Fibonacci memory contents
        $display("=== FIBONACCI SEQUENCE IN MEMORY ===");
        for (int i = 0; i < 10; i++) begin
            fib_value = uut.data_mem_inst.memory_array[i];
            $display(" Fib(%0d) = %0d", i+1, fib_value);
        end

        // Verify against expected
        correct_count = 0;
        for (int i = 0; i < uut.dp_inst.rf.registers[5] && i < 10; i++) begin
            if (uut.data_mem_inst.memory_array[i] == expected_fib[i]) begin
                correct_count++;
            end
        end
        $display("\nVerification: %0d/%0d correct values", correct_count, uut.dp_inst.rf.registers[5]);
        if (correct_count >= 5) begin
            $display("✓ Fibonacci calculation is working correctly!");
        end else begin
            $display("✗ Fibonacci calculation has errors");
        end

        $finish;
    end

    // Instruction tracking on each clock
    always @(posedge clk) begin
        if (!rst) begin
            cycle_count++;
            case (uut.instruction[6:0])
                7'b0000011: load_count++;
                7'b0100011: store_count++;
                7'b0110011: begin
                    case (uut.instruction[14:12])
                        3'b000: if (uut.instruction[30]) sub_count++; else add_count++;
                        3'b111: and_count++;
                        3'b110: or_count++;
                    endcase
                end
                7'b1100011: beq_count++;
                7'b0010011: addi_count++;
            endcase

            if (uut.instruction != 32'h00000013) begin
                total_instr++;
                if (cycle_count <= 20) begin
                    $display("CYCLE %0d | PC: 0x%02h | Instr: 0x%h | Type: %s | R1: %0d | R2: %0d | R3: %0d | R5: %0d | R31: %0d", 
                             cycle_count,
                             uut.pc[7:0],
                             uut.instruction,
                             get_instr_type(uut.instruction),
                             uut.dp_inst.rf.registers[1],
                             uut.dp_inst.rf.registers[2],
                             uut.dp_inst.rf.registers[3],
                             uut.dp_inst.rf.registers[5],
                             uut.dp_inst.rf.registers[31]);
                end
            end

            if (cycle_count % 20 == 0) begin
                $display("--- Cycle %0d: computed %0d fib numbers ---", cycle_count, uut.dp_inst.rf.registers[5]);
            end

            if (cycle_count > 200) begin
                $display("Stopping simulation after 200 cycles");
                $finish;
            end
        end
    end

    // Helper: decode instruction type
    function string get_instr_type(logic [31:0] instr);
        case (instr[6:0])
            7'b0000011: get_instr_type = "LD";
            7'b0100011: get_instr_type = "SD";
            7'b0110011: begin
                case (instr[14:12])
                    3'b000: get_instr_type = instr[30] ? "SUB" : "ADD";
                    3'b111: get_instr_type = "AND";
                    3'b110: get_instr_type = "OR";
                    default: get_instr_type = "R-TYPE";
                endcase
            end
            7'b1100011: get_instr_type = "BEQ";
            7'b0010011: get_instr_type = "ADDI";
            default:      get_instr_type = "UNKNOWN";
        endcase
    endfunction

endmodule

fibo_comp.vcd
$date
	Wed Jun 11 08:28:14 2025
$end
$version
	Icarus Verilog
$end
$timescale
	1ps
$end
$scope module tb_fibonacci_comprehensive $end
$var wire 64 ! debug_out [63:0] $end
$var reg 1 " clk $end
$var reg 64 # fib_value [63:0] $end
$var reg 1 $ rst $end
$var integer 32 % add_count [31:0] $end
$var integer 32 & addi_count [31:0] $end
$var integer 32 ' and_count [31:0] $end
$var integer 32 ( beq_count [31:0] $end
$var integer 32 ) correct_count [31:0] $end
$var integer 32 * cycle_count [31:0] $end
$var integer 32 + load_count [31:0] $end
$var integer 32 , or_count [31:0] $end
$var integer 32 - store_count [31:0] $end
$var integer 32 . sub_count [31:0] $end
$var integer 32 / total_instr [31:0] $end
$scope function get_instr_type $end
$var reg 32 0 instr [31:0] $end
$upscope $end
$scope module uut $end
$var wire 1 " clk $end
$var wire 1 $ rst $end
$var wire 1 1 zero $end
$var wire 64 2 write_data_memory [63:0] $end
$var wire 1 3 reg_write $end
$var wire 64 4 read_data_memory [63:0] $end
$var wire 5 5 rd_addr [4:0] $end
$var wire 64 6 pc [63:0] $end
$var wire 1 7 mem_write $end
$var wire 1 8 mem_to_reg $end
$var wire 1 9 mem_read $end
$var wire 32 : instruction [31:0] $end
$var wire 64 ; imm [63:0] $end
$var wire 64 < debug_out [63:0] $end
$var wire 1 = branch $end
$var wire 1 > alu_src $end
$var wire 64 ? alu_result [63:0] $end
$var wire 3 @ alu_control [2:0] $end
$scope module cu_inst $end
$var wire 3 A funct3 [2:0] $end
$var wire 7 B funct7 [6:0] $end
$var wire 7 C opcode [6:0] $end
$var reg 3 D alu_control [2:0] $end
$var reg 1 > alu_src $end
$var reg 1 = branch $end
$var reg 1 9 mem_read $end
$var reg 1 8 mem_to_reg $end
$var reg 1 7 mem_write $end
$var reg 1 3 reg_write $end
$upscope $end
$scope module data_mem_inst $end
$var wire 32 E addr [31:0] $end
$var wire 1 " clk $end
$var wire 1 F rd_enable $end
$var wire 1 $ rst $end
$var wire 1 7 wr_enable $end
$var wire 64 G wr_data [63:0] $end
$var wire 32 H word_addr [31:0] $end
$var wire 64 I rd_data [63:0] $end
$var parameter 32 J mem_size $end
$var parameter 176 K rom_file $end
$var parameter 32 L rom_size $end
$var integer 32 M i [31:0] $end
$upscope $end
$scope module dp_inst $end
$var wire 3 N alu_control [2:0] $end
$var wire 1 > alu_src $end
$var wire 1 " clk $end
$var wire 1 8 mem_to_reg $end
$var wire 64 O read_data_memory [63:0] $end
$var wire 1 3 reg_write $end
$var wire 1 $ rst $end
$var wire 64 P write_data_memory [63:0] $end
$var wire 1 1 zero $end
$var wire 64 Q wb_data [63:0] $end
$var wire 64 R rs2_data [63:0] $end
$var wire 5 S rs2 [4:0] $end
$var wire 64 T rs1_data [63:0] $end
$var wire 5 U rs1 [4:0] $end
$var wire 5 V rd_addr [4:0] $end
$var wire 32 W instruction [31:0] $end
$var wire 64 X imm [63:0] $end
$var wire 64 Y debug_out [63:0] $end
$var wire 64 Z alu_result [63:0] $end
$var wire 64 [ alu_b [63:0] $end
$scope module alu_inst $end
$var wire 3 \ alu_control [2:0] $end
$var wire 64 ] b [63:0] $end
$var wire 1 1 zero $end
$var wire 64 ^ a [63:0] $end
$var reg 64 _ result [63:0] $end
$upscope $end
$scope module rf $end
$var wire 1 " clk $end
$var wire 64 ` debug_output [63:0] $end
$var wire 5 a rd_addr1 [4:0] $end
$var wire 5 b rd_addr2 [4:0] $end
$var wire 1 $ rst $end
$var wire 5 c wr_addr [4:0] $end
$var wire 64 d wr_data [63:0] $end
$var wire 1 3 wr_enable $end
$var wire 64 e rd_data2 [63:0] $end
$var wire 64 f rd_data1 [63:0] $end
$var integer 32 g i [31:0] $end
$upscope $end
$upscope $end
$scope module instr_mem_inst $end
$var wire 32 h address [31:0] $end
$var wire 32 i word_addr [31:0] $end
$var wire 32 j instruction [31:0] $end
$var parameter 176 k mem_file $end
$var parameter 32 l mem_size $end
$var integer 32 m i [31:0] $end
$upscope $end
$scope module pc_inst $end
$var wire 1 = branch $end
$var wire 1 " clk $end
$var wire 1 $ rst $end
$var wire 1 n take_branch $end
$var wire 1 1 zero $end
$var wire 64 o imm [63:0] $end
$var reg 64 p pc [63:0] $end
$var reg 64 q pc_next [63:0] $end
$upscope $end
$scope module sign_ext_inst $end
$var wire 32 r instr [31:0] $end
$var wire 64 s imm_s [63:0] $end
$var wire 64 t imm_out [63:0] $end
$var wire 64 u imm_i [63:0] $end
$var wire 64 v imm_b [63:0] $end
$upscope $end
$upscope $end
$scope begin $ivl_for_loop0 $end
$var integer 32 w i [31:0] $end
$upscope $end
$scope begin $ivl_for_loop1 $end
$var integer 32 x i [31:0] $end
$upscope $end
$upscope $end
$enddefinitions $end
$comment Show the parameter values. $end
$dumpall
b10001 l
b1110000011100100110111101100111011100100110000101101101011100110010111101100110011010010110001001101111010111110110001101101111011011010111000000101110011011010110010101101101 k
b10 L
b1110000011100100110111101100111011100100110000101101101011100110010111101100110011010010110001001101111010111110110010001100001011101000110000100101110011011010110010101101101 K
b100000000 J
$end
#0
$dumpvars
b0 x
b0 w
b100000000000 v
b0 u
b0 t
b1 s
b11000010000011 r
b100 q
b0 p
b0 o
0n
b10001 m
b11000010000011 j
b0 i
b0 h
b100000 g
b0 f
b0 e
b1 d
b1 c
b0 b
b0 a
b0 `
b0 _
b0 ^
b0 ]
b0 \
b0 [
b0 Z
b0 Y
b0 X
b11000010000011 W
b1 V
b0 U
b0 T
b0 S
b0 R
b1 Q
b0 P
b1 O
b0 N
b10 M
b1 I
b0 H
b0 G
1F
b0 E
b0 D
b11 C
b0 B
b11 A
b0 @
b0 ?
1>
0=
b0 <
b0 ;
b11000010000011 :
19
18
07
b0 6
b1 5
b1 4
13
b0 2
11
bx 0
b0 /
b0 .
b0 -
b0 ,
b0 +
b0 *
b0 )
b0 (
b0 '
b0 &
b0 %
1$
bx #
0"
b0 !
$end
#5000
b100000 g
1"
#10000
0"
#15000
b100000 g
1"
#20000
0"
0$
#25000
b1 H
b1000 E
b1000 ;
b1000 o
b1000 t
01
b1000 ?
b1000 Z
b1000 _
b1000 [
b1000 ]
b1000 u
b10 s
b10 v
b1000 X
b10 5
b10 V
b10 c
b1000 S
b1000 b
b100000000011000100000011 :
b100000000011000100000011 W
b100000000011000100000011 j
b100000000011000100000011 r
b1 i
b1000 q
b100 h
b100 6
b100 p
b11000010000011 0
b1 /
b1 +
b1 *
1"
#30000
0"
#35000
b0 H
b0 E
b0 ;
b0 o
b0 t
11
b0 ?
b0 Z
b0 _
b0 Q
b0 d
b0 [
b0 ]
1>
08
09
13
b0 u
b11111 s
b100000011110 v
b0 X
b11111 5
b11111 V
b11111 c
b0 S
b0 b
b0 A
b10011 C
b111110010011 :
b111110010011 W
b111110010011 j
b111110010011 r
b10 i
b1100 q
b1000 h
b1000 6
b1000 p
b100000000011000100000011 0
b10 /
b10 +
b10 *
1"
#40000
0"
#45000
b1 H
b1010 Q
b1010 d
b1010 E
b1010 ;
b1010 o
b1010 t
01
b1010 ?
b1010 Z
b1010 _
b1010 [
b1010 ]
b1010 u
b100 s
b100 v
b1010 X
b100 5
b100 V
b100 c
b1010 S
b1010 b
b101000000000001000010011 :
b101000000000001000010011 W
b101000000000001000010011 j
b101000000000001000010011 r
b11 i
b10000 q
b1100 h
b1100 6
b1100 p
b111110010011 0
b11 /
b1 &
b11 *
1"
#50000
0"
#55000
b0 H
b0 Q
b0 d
b0 E
b0 ;
b0 o
b0 t
11
b0 ?
b0 Z
b0 _
b0 [
b0 ]
b0 u
b101 s
b100000000100 v
b0 X
b101 5
b101 V
b101 c
b0 S
b0 b
b1010010011 :
b1010010011 W
b1010010011 j
b1010010011 r
b100 i
b10100 q
b10000 h
b10000 6
b10000 p
b101000000000001000010011 0
b100 /
b10 &
b100 *
1"
#60000
0"
#65000
b10 Q
b10 d
b10 E
b10 ;
b10 o
b10 t
01
b10 ?
b10 Z
b10 _
b1 [
b1 ]
b1 2
b1 G
b1 P
b1 R
b1 e
b1 T
b1 ^
b1 f
0>
13
b10 u
b11 s
b100000000010 v
b10 X
b11 5
b11 V
b11 c
b10 S
b10 b
b1 U
b1 a
b110011 C
b1000001000000110110011 :
b1000001000000110110011 W
b1000001000000110110011 j
b1000001000000110110011 r
b101 i
b11000 q
b10100 h
b10100 6
b10100 p
b1010010011 0
b101 /
b11 &
b101 *
1"
#70000
0"
#75000
b101 Q
b101 d
b101 E
b11 ;
b11 o
b11 t
b101 ?
b101 Z
b101 _
b11 [
b11 ]
b10 2
b10 G
b10 P
b10 R
b10 e
b10 T
b10 ^
b10 f
1>
13
b11 u
b11111 s
b100000011110 v
b11 X
b11111 5
b11111 V
b11111 c
b11 S
b11 b
b11 U
b11 a
b10011 C
b1100011000111110010011 :
b1100011000111110010011 W
b1100011000111110010011 j
b1100011000111110010011 r
b110 i
b11100 q
b11000 h
b11000 6
b11000 p
b1000001000000110110011 0
b110 /
b1 %
b110 *
1"
#80000
0"
#85000
b1 Q
b1 d
b1 E
b0 ;
b0 o
b0 t
b1 ?
b1 Z
b1 _
b0 [
b0 ]
b0 2
b0 G
b0 P
b0 R
b0 e
b1 T
b1 ^
b1 f
b0 u
b1 s
b100000000000 v
b0 X
b1 5
b1 V
b1 c
b0 S
b0 b
b10 U
b10 a
b10000000010010011 :
b10000000010010011 W
b10000000010010011 j
b10000000010010011 r
b111 i
b100000 q
b11100 h
b101 !
b101 <
b101 Y
b101 `
b11100 6
b11100 p
b1100011000111110010011 0
b111 /
b100 &
b111 *
1"
#90000
0"
#95000
b10 Q
b10 d
b10 E
b10 ?
b10 Z
b10 _
b10 T
b10 ^
b10 f
b10 s
b10 v
b10 5
b10 V
b10 c
b11 U
b11 a
b11000000100010011 :
b11000000100010011 W
b11000000100010011 j
b11000000100010011 r
b1000 i
b100100 q
b100000 h
b100000 6
b100000 p
b10000000010010011 0
b1000 /
b101 &
b1000 *
1"
#100000
0"
#105000
b101 Q
b101 d
b101 E
b101 ?
b101 Z
b101 _
b101 [
b101 ]
b0 T
b0 ^
b0 f
17
1>
03
b101 u
b0 s
b0 v
b101 X
b0 5
b0 V
b0 c
b101 S
b101 b
b101 U
b101 a
b100011 C
b10100101000000000100011 :
b10100101000000000100011 W
b10100101000000000100011 j
b10100101000000000100011 r
b1001 i
b101000 q
b100100 h
b100100 6
b100100 p
b11000000100010011 0
b1001 /
b110 &
b1001 *
1"
#110000
0"
#115000
b1 Q
b1 d
b1 E
b1 ?
b1 Z
b1 _
b1 ;
b1 o
b1 t
b1 [
b1 ]
b1 2
b1 G
b1 P
b1 R
b1 e
13
1>
07
b1 u
b101 s
b100000000100 v
b1 X
b101 5
b101 V
b101 c
b1 S
b1 b
b10011 C
b100101000001010010011 :
b100101000001010010011 W
b100101000001010010011 j
b100101000001010010011 r
b1010 i
b101100 q
b101000 h
b101000 6
b101000 p
b10100101000000000100011 0
b1010 /
b1 -
b1010 *
1"
#120000
0"
#125000
b11 ;
b11 o
b11 t
11
b10 [
b10 ]
b10 2
b10 G
b10 P
b10 R
b10 e
b10 @
b10 D
b10 N
b10 \
0>
13
b11 u
b11110 s
b11110 v
b11 X
b11110 5
b11110 V
b11110 c
b11 S
b11 b
b11110 U
b11110 a
b111 A
b110011 C
b0 Q
b0 d
b0 E
b1111110111111100110011 :
b1111110111111100110011 W
b1111110111111100110011 j
b1111110111111100110011 r
b0 ?
b0 Z
b0 _
b1011 i
b0 T
b0 ^
b0 f
b110000 q
b101100 h
b101100 6
b101100 p
b100101000001010010011 0
b1011 /
b111 &
b1011 *
1"
#130000
0"
#135000
b10 Q
b10 d
b10 E
01
b10 ?
b10 Z
b10 _
13
b11 @
b11 D
b11 N
b11 \
b11100 s
b11100 v
b11100 5
b11100 V
b11100 c
b11101 U
b11101 a
b110 A
b1111101110111000110011 :
b1111101110111000110011 W
b1111101110111000110011 j
b1111101110111000110011 r
b1100 i
b110100 q
b110000 h
b110000 6
b110000 p
b1111110111111100110011 0
b1100 /
b1 '
b1100 *
1"
#140000
0"
