src/definitions.sv
`ifndef DEFINITIONS_SV
`define DEFINITIONS_SV

// ALU control signals
`define ALU_ADD 3'b000
`define ALU_SUB 3'b001
`define ALU_AND 3'b010
`define ALU_OR  3'b011

// Opcode definitions (no JAL, only these 4 types)
`define OP_R_TYPE   7'b0110011  // ADD, SUB, AND, OR
`define OP_I_TYPE   7'b0000011  // LD  (Load Double)
`define OP_S_TYPE   7'b0100011  // SD  (Store Double)
`define OP_B_TYPE   7'b1100011  // BEQ (Branch if Equal) 

// Function codes for R‑type
`define FUNC3_ADD_SUB 3'b000
`define FUNC3_AND     3'b111
`define FUNC3_OR      3'b110

`define FUNC7_ADD     7'b0000000
`define FUNC7_SUB     7'b0100000

`endif

src/alu.sv
`include "definitions.sv"

module alu (
    input  logic [63:0] a,
    input  logic [63:0] b,
    input  logic [2:0]  alu_control,
    output logic [63:0] result,
    output logic        zero
);

    always_comb begin
        case (alu_control)
            `ALU_ADD: result = a + b;
            `ALU_SUB: result = a - b;
            `ALU_AND: result = a & b;
            `ALU_OR:  result = a | b;
            default:  result = a + b;
        endcase
    end

    assign zero = (result == 64'b0);

endmodule

reg_file_gaurav.sv
module reg_file(
    input logic clk,
    input logic rst,
    input logic[4:0] rd_addr1,
    output logic[63:0] rd_data1,
    input logic[4:0] rd_addr2,
    output logic[63:0] rd_data2,
    input logic[4:0] wr_addr,
    input logic[63:0] wr_data,
    input logic wr_enable,

    output logic[63:0] debug_output //reg 31 which is connected to output pins
);
logic [63:0] registers[31:0];

always_ff@(posedge clk or posedge rst) begin
    if(rst) begin
        for(int i=0;i<32;i++) begin
            registers[i]<=64'b0;
        end
    end
    else if(wr_enable) begin
        registers[wr_addr]<=wr_data;
    end
end

assign rd_data1=registers[rd_addr1];
assign rd_data2=registers[rd_addr2];

assign debug_output=registers[31];

endmodule

src/data_path.sv
module datapath (
    input  logic        clk,
    input  logic        rst,
    input  logic [31:0] instruction,
    input  logic [63:0] read_data_memory,
    input  logic [2:0]  alu_control,
    input  logic        reg_write,
    input  logic        alu_src,
    input  logic        mem_to_reg,

    output logic [63:0] alu_result,
    output logic [63:0] write_data_memory,
    output logic [4:0]  rd_addr,
    output logic        zero,
    output logic [63:0] debug_out  // (optional) contents of x31
);

    // Register‑file wires
    logic [63:0] rs1_data, rs2_data;
    logic [63:0] imm;
    logic [63:0] alu_b;
    logic [63:0] wb_data;

    // Decode register indices
    logic [4:0] rs1 = instruction[19:15]; 
    logic [4:0] rs2 = instruction[24:20];
    assign rd_addr = instruction[11:7];

    // Instantiate register file
    reg_file rf (
        .clk        (clk),
        .rst        (rst),
        .rd_addr1   (rs1),
        .rd_data1   (rs1_data),
        .rd_addr2   (rs2),
        .rd_data2   (rs2_data),
        .wr_addr    (rd_addr),
        .wr_data    (wb_data),
        .wr_enable  (reg_write),
        .debug_output(debug_out)
    );

    // Sign‑extended immediate (LD / BEQ)
    assign imm   = {{52{instruction[31]}}, instruction[31:20]};

    // ALU input mux: either register or immediate
    assign alu_b = (alu_src) ? imm : rs2_data;

    // Launch ALU
    alu alu_inst (
        .a           (rs1_data),
        .b           (alu_b),
        .alu_control (alu_control),
        .result      (alu_result),
        .zero        (zero)
    );

    // Data memory will write rs2_data
    assign write_data_memory = rs2_data;

    // Write‑back mux: from memory or from ALU
    assign wb_data = (mem_to_reg) ? read_data_memory : alu_result;

endmodule

src/data_mem.sv
module data_mem #(
    parameter mem_size=256, //size in terms of 64 bit words
    parameter rom_size=4,
    parameter rom_file="programs/data.mem" //file to initialize rom
)(
    input logic clk,
    input logic rst,
    input logic[31:0] addr, //byte address
    input logic[63:0] wr_data,
    input logic wr_enable,
    input logic rd_enable,
    output logic[63:0] rd_data
);

logic[63:0] memory[0:mem_size-1]; //data memory

//convert byte address to word address 
logic[31:0] word_addr=addr[31:3];

initial begin
    for(int i=0;i<mem_size;i++) begin
        memory[i]=64'b0;
    end
    //load rom region into data memory
    $readmemh(rom_file,memory,0,rom_size-1);
end

always_ff@(posedge clk or posedge rst) begin
    if(rst) begin
        for(int i=rom_size;i<mem_size;i++) begin //only reset ram portion
            memory[i]<=64'b0;
        end
    end
    else if(wr_enable) begin
        //only allow writing to ram region
        if(word_addr>=rom_size) begin
            memory[word_addr]<=wr_data;
        end
        else begin
            $display("Attempt to write to ROM region");
        end
    end
end

always_comb begin 
    if(rd_enable) begin
        rd_data=memory[word_addr];
    end
    else begin
        //if read not enabled output 0
        rd_data=64'b0;
    end
end

endmodule

src/control_unit.sv
// File: src/control_unit.sv
`include "definitions.sv"

module control_unit (
    input  logic [6:0] opcode,
    input  logic [2:0] funct3,
    input  logic [6:0] funct7,
    output logic [2:0] alu_control,   // ALU operation select
    output logic       reg_write,     // Write to register file?
    output logic       mem_read,      // Read from data_mem?
    output logic       mem_write,     // Write to data_mem?
    output logic       mem_to_reg,    // Write-back: memory or ALU?
    output logic       alu_src,       // ALU second input = immediate?
    output logic       branch         // BEQ?
);

    always_comb begin
        // Defaults
        alu_control = `ALU_ADD;
        reg_write   = 1'b0;
        mem_read    = 1'b0;
        mem_write   = 1'b0;
        mem_to_reg  = 1'b0;
        alu_src     = 1'b0;
        branch      = 1'b0;

        // If opcode is all X's (unknown), do nothing
        if (opcode === 7'bxxxxxxx) begin
            // keep defaults; no warning
        end else begin
            case (opcode)
                // I-Type (LD)
                `OP_I_TYPE: begin
                    alu_control = `ALU_ADD;
                    reg_write   = 1'b1;
                    mem_read    = 1'b1;
                    mem_write   = 1'b0;
                    mem_to_reg  = 1'b1;
                    alu_src     = 1'b1;
                    branch      = 1'b0;
                end

                // I-Type ALU operations (ADDI, etc.)
                `OP_I_ALU: begin
                    alu_control = `ALU_ADD;
                    reg_write   = 1'b1;
                    mem_read    = 1'b0;
                    mem_write   = 1'b0;
                    mem_to_reg  = 1'b0;
                    alu_src     = 1'b1;  // Use immediate
                    branch      = 1'b0;
                end

                // S-Type (SD)
                `OP_S_TYPE: begin
                    alu_control = `ALU_ADD;
                    reg_write   = 1'b0;
                    mem_read    = 1'b0;
                    mem_write   = 1'b1;
                    mem_to_reg  = 1'b0;
                    alu_src     = 1'b1;
                    branch      = 1'b0;
                end

                // R-Type (ADD/SUB/AND/OR)
                `OP_R_TYPE: begin
                    alu_control = `ALU_ADD;
                    reg_write   = 1'b1;
                    mem_read    = 1'b0;
                    mem_write   = 1'b0;
                    mem_to_reg  = 1'b0;
                    alu_src     = 1'b0;
                    branch      = 1'b0;
                end

                // B-Type (BEQ)
                `OP_B_TYPE: begin
                    alu_control = `ALU_SUB;
                    reg_write   = 1'b0;
                    mem_read    = 1'b0;
                    mem_write   = 1'b0;
                    mem_to_reg  = 1'b0;
                    alu_src     = 1'b0;
                    branch      = 1'b1;
                end

                default: begin
                    $display("Warning: Unknown opcode: 0x%h", opcode);
                end
            endcase
        end
    end

endmodule

src/sign_extend.sv
module sign_extend (
    input  logic [31:0] instr,
    output logic [63:0] imm_out
);
    // Extract opcode
    wire [6:0] opcode;
    assign opcode = instr[6:0];
    
    // Create all possible immediate values
    wire [63:0] i_imm_ext, s_imm_ext, b_imm_ext;
    
    assign i_imm_ext = {{52{instr[31]}}, instr[31:20]};
    assign s_imm_ext = {{52{instr[31]}}, instr[31:25], instr[11:7]};
    assign b_imm_ext = {{51{instr[31]}}, instr[31], instr[7], instr[30:25], instr[11:8], 1'b0};
    
    // Select the right one based on opcode
    assign imm_out = (opcode == `OP_I_TYPE) ? i_imm_ext :
                     (opcode == `OP_S_TYPE) ? s_imm_ext :
                     (opcode == `OP_B_TYPE) ? b_imm_ext : 64'b0;
endmodule

src/instr_mem.sv
module instr_mem #(
    parameter mem_size = 256,  //no of instruction words
    parameter mem_file = "programs/program.mem"  
) (
    input  logic [31:0] address,     //address of instruction to read (byte address)
    output logic [31:0] instruction  //instruction at that address
);

    logic [31:0] memory [0:mem_size-1];

    initial begin
        //initialize all memory to NOP instructions first
        for (int i = 0; i < mem_size; i++) begin
            memory[i] = 32'h00000003; 
        end
        
        //load instructions from the .mem file
        $readmemh(mem_file, memory, 0, 5);  // for 6 instructions
        
    end
    
    //asynchronous read 
    //convert byte address to word address by dividing by 4 
    assign instruction = memory[address[31:2]];

endmodule

src/pc_logic.sv
module pc_logic (
    input  logic        clk,
    input  logic        rst,
    input  logic        branch,
    input  logic        zero,
    input  logic [63:0] imm,
    output logic [63:0] pc
);

    always_ff @(posedge clk or posedge rst) begin
        if (rst) begin
            pc <= 64'b0;
        end else begin
            pc <= pc + 64'd4;  // Simple increment, ignore branches for now
        end
    end

endmodule

src/single_cycle_cpu.sv
`include "definitions.sv"

module single_cycle_cpu (
    input  logic clk,
    input  logic rst,
    output logic [63:0] debug_out  // Output from register x31 for monitoring
);

    // Program counter
    logic [63:0] pc;
    logic [31:0] instruction;
    logic [63:0] imm;

    // Control signals (removed jump)
    logic [2:0] alu_control;
    logic reg_write, mem_read, mem_write, mem_to_reg;
    logic alu_src, branch;

    // Datapath to memory connections
    logic [63:0] alu_result, write_data_memory;
    logic [4:0] rd_addr;
    logic [63:0] read_data_memory;
    logic zero;

    // Instantiate PC logic (removed jump signal)
    pc_logic pc_module (
        .clk(clk),
        .rst(rst),
        .branch(branch),
        .zero(zero),
        .imm(imm),
        .pc(pc)
    );

    // Instruction Memory (ROM)
    instr_mem instr_mem_inst (
        .address(pc[31:0]),          // 32-bit PC used as byte address
        .instruction(instruction)
    );

    // Sign Extension
    sign_extend sign_ext_inst (
        .instr(instruction),
        .imm_out(imm)
    );

    // Control Unit (removed jump signal)
    control_unit cu (
        .opcode (instruction[6:0]),
        .funct3 (instruction[14:12]),
        .funct7 (instruction[31:25]),
        .alu_control(alu_control),
        .reg_write(reg_write),
        .mem_read(mem_read),
        .mem_write(mem_write),
        .mem_to_reg(mem_to_reg),
        .alu_src(alu_src),
        .branch(branch)
    );

    // Data Memory
    data_mem data_memory (
        .clk(clk),
        .rst(rst),
        .addr(alu_result[31:0]),
        .wr_data(write_data_memory),
        .wr_enable(mem_write),
        .rd_enable(mem_read),
        .rd_data(read_data_memory)
    );

    // Datapath
    datapath datapath_inst (
        .clk(clk),
        .rst(rst),
        .instruction(instruction),
        .read_data_memory(read_data_memory),
        .alu_control(alu_control),
        .reg_write(reg_write),
        .alu_src(alu_src),
        .mem_to_reg(mem_to_reg),
        .alu_result(alu_result),
        .write_data_memory(write_data_memory),
        .rd_addr(rd_addr),
        .zero(zero),
        .debug_out(debug_out)
    );

endmodule

testbench/tb_single_cycle_cpu.sv
// testbench:
`timescale 1ns/1ps
module tb_single_cycle_cpu;
    logic clk, rst;
    logic [63:0] debug_out;

    single_cycle_cpu uut (
        .clk(clk),
        .rst(rst),
        .debug_out(debug_out)
    );

    // Clock generation
    initial clk = 0;
    always #5 clk = ~clk;  // 100MHz clock

    // Simulation control
    initial begin
        $dumpfile("waveform.vcd");
        $dumpvars(0, tb_single_cycle_cpu);
        rst = 1;
        #15;
        rst = 0;

        // Run simulation for 500ns
        #500 $finish;
    end
endmodule

waveform.vcd
$date
	Thu Jun 05 11:12:55 2025
$end
$version
	Icarus Verilog
$end
$timescale
	1ps
$end
$scope module tb_single_cycle_cpu $end
$var wire 64 ! debug_out [63:0] $end
$var reg 1 " clk $end
$var reg 1 # rst $end
$scope module uut $end
$var wire 1 " clk $end
$var wire 1 # rst $end
$var wire 1 $ zero $end
$var wire 64 % write_data_memory [63:0] $end
$var wire 1 & reg_write $end
$var wire 64 ' read_data_memory [63:0] $end
$var wire 5 ( rd_addr [4:0] $end
$var wire 64 ) pc [63:0] $end
$var wire 1 * mem_write $end
$var wire 1 + mem_to_reg $end
$var wire 1 , mem_read $end
$var wire 32 - instruction [31:0] $end
$var wire 64 . imm [63:0] $end
$var wire 64 / debug_out [63:0] $end
$var wire 1 0 branch $end
$var wire 1 1 alu_src $end
$var wire 64 2 alu_result [63:0] $end
$var wire 3 3 alu_control [2:0] $end
$scope module cu $end
$var wire 3 4 funct3 [2:0] $end
$var wire 7 5 funct7 [6:0] $end
$var wire 7 6 opcode [6:0] $end
$var reg 3 7 alu_control [2:0] $end
$var reg 1 1 alu_src $end
$var reg 1 0 branch $end
$var reg 1 , mem_read $end
$var reg 1 + mem_to_reg $end
$var reg 1 * mem_write $end
$var reg 1 & reg_write $end
$upscope $end
$scope module data_memory $end
$var wire 32 8 addr [31:0] $end
$var wire 1 " clk $end
$var wire 1 , rd_enable $end
$var wire 1 # rst $end
$var wire 1 * wr_enable $end
$var wire 64 9 wr_data [63:0] $end
$var parameter 32 : mem_size $end
$var parameter 136 ; rom_file $end
$var parameter 32 < rom_size $end
$var reg 64 = rd_data [63:0] $end
$var reg 32 > word_addr [31:0] $end
$scope begin $ivl_for_loop0 $end
$var integer 32 ? i [31:0] $end
$upscope $end
$scope begin $ivl_for_loop1 $end
$var integer 32 @ i [31:0] $end
$upscope $end
$upscope $end
$scope module datapath_inst $end
$var wire 3 A alu_control [2:0] $end
$var wire 1 1 alu_src $end
$var wire 1 " clk $end
$var wire 1 + mem_to_reg $end
$var wire 64 B read_data_memory [63:0] $end
$var wire 1 & reg_write $end
$var wire 1 # rst $end
$var wire 64 C write_data_memory [63:0] $end
$var wire 1 $ zero $end
$var wire 64 D wb_data [63:0] $end
$var wire 64 E rs2_data [63:0] $end
$var wire 64 F rs1_data [63:0] $end
$var wire 5 G rd_addr [4:0] $end
$var wire 32 H instruction [31:0] $end
$var wire 64 I imm [63:0] $end
$var wire 64 J debug_out [63:0] $end
$var wire 64 K alu_result [63:0] $end
$var wire 64 L alu_b [63:0] $end
$var reg 5 M rs1 [4:0] $end
$var reg 5 N rs2 [4:0] $end
$scope module alu_inst $end
$var wire 3 O alu_control [2:0] $end
$var wire 64 P b [63:0] $end
$var wire 1 $ zero $end
$var wire 64 Q a [63:0] $end
$var reg 64 R result [63:0] $end
$upscope $end
$scope module rf $end
$var wire 1 " clk $end
$var wire 64 S debug_output [63:0] $end
$var wire 5 T rd_addr1 [4:0] $end
$var wire 5 U rd_addr2 [4:0] $end
$var wire 64 V rd_data1 [63:0] $end
$var wire 64 W rd_data2 [63:0] $end
$var wire 1 # rst $end
$var wire 5 X wr_addr [4:0] $end
$var wire 64 Y wr_data [63:0] $end
$var wire 1 & wr_enable $end
$scope begin $ivl_for_loop3 $end
$var integer 32 Z i [31:0] $end
$upscope $end
$upscope $end
$upscope $end
$scope module instr_mem_inst $end
$var wire 32 [ address [31:0] $end
$var wire 32 \ instruction [31:0] $end
$var parameter 160 ] mem_file $end
$var parameter 32 ^ mem_size $end
$scope begin $ivl_for_loop2 $end
$var integer 32 _ i [31:0] $end
$upscope $end
$upscope $end
$scope module pc_module $end
$var wire 1 0 branch $end
$var wire 1 " clk $end
$var wire 1 # rst $end
$var wire 1 $ zero $end
$var wire 64 ` imm [63:0] $end
$var reg 64 a pc [63:0] $end
$upscope $end
$scope module sign_ext_inst $end
$var wire 32 b instr [31:0] $end
$var wire 64 c s_imm_ext [63:0] $end
$var wire 7 d opcode [6:0] $end
$var wire 64 e imm_out [63:0] $end
$var wire 64 f i_imm_ext [63:0] $end
$var wire 64 g b_imm_ext [63:0] $end
$upscope $end
$upscope $end
$upscope $end
$enddefinitions $end
$comment Show the parameter values. $end
$dumpall
b100000000 ^
b111000001110010011011110110011101110010011000010110110101110011001011110111000001110010011011110110011101110010011000010110110100101110011011010110010101101101 ]
b100 <
b111000001110010011011110110011101110010011000010110110101110011001011110110010001100001011101000110000100101110011011010110010101101101 ;
b100000000 :
$end
#0
$dumpvars
b100000000000 g
b0 f
b0 e
b110011 d
b1 c
b1000000010110011 b
b0 a
b0 `
b100000000 _
b1000000010110011 \
b0 [
b100000 Z
bx Y
b1 X
bx W
bx V
bx U
bx T
b0 S
bx R
bx Q
bx P
b0 O
bx N
bx M
bx L
bx K
b0 J
b0 I
b1000000010110011 H
b1 G
bx F
bx E
bx D
bx C
b0 B
b0 A
b100000000 @
b100000000 ?
b0zzzzzzzzzzzzzzzzzzzzzzzzzzzzz >
b0 =
bx 9
bx 8
b0 7
b110011 6
b0 5
b0 4
b0 3
bx 2
01
00
b0 /
b0 .
b1000000010110011 -
0,
0+
0*
b0 )
b1 (
b0 '
1&
bx %
x$
1#
0"
b0 !
$end
#5000
b100000 Z
b100000000 @
1"
#10000
0"
#15000
b10 c
b10 g
b10 (
b10 G
b10 X
b10000000100110011 -
b10000000100110011 H
b10000000100110011 \
b10000000100110011 b
b100 [
b100 )
b100 a
1"
0#
#20000
0"
#25000
b1000 L
b1000 P
11
1*
0&
b100011 d
b1000 f
b0 c
b0 g
b1000 I
b0 (
b0 G
b0 X
b10 4
b100011 6
b100000010010000000100011 -
b100000010010000000100011 H
b100000010010000000100011 \
b100000010010000000100011 b
b1000 [
b1000 )
b1000 a
1"
#30000
0"
#35000
bx '
bx =
bx B
b1000 .
b1000 `
b1000 e
1+
1,
1&
11
0*
b11 d
b11 c
b100000000010 g
b11 (
b11 G
b11 X
b11 6
b100000010010000110000011 -
b100000010010000110000011 H
b100000010010000110000011 \
b100000010010000110000011 b
b1100 [
b1100 )
b1100 a
1"
#40000
0"
#45000
b0 '
b0 =
b0 B
b10000001100 .
b10000001100 `
b10000001100 e
bx L
bx P
10
b1 3
b1 7
b1 A
b1 O
01
0+
0,
0&
b1100011 d
b10000000011 f
b10000001100 c
b10000001100 g
b10000000011 I
b1100 (
b1100 G
b1100 X
b100000 5
b0 4
b1100011 6
b1000000001100011000011001100011 -
b1000000001100011000011001100011 H
b1000000001100011000011001100011 \
b1000000001100011000011001100011 b
b10000 [
b10000 )
b10000 a
1"
#50000
0"
#55000
b0 .
b0 `
b0 e
00
b0 3
b0 7
b0 A
b0 O
b10011 d
b0 f
b0 c
b0 g
b0 I
b0 (
b0 G
b0 X
b0 5
b10011 6
b10011 -
b10011 H
b10011 \
b10011 b
b10100 [
b10100 )
b10100 a
1"
#60000
0"
#65000
b0 L
b0 P
bx '
bx =
bx B
11
1+
1,
1&
b11 d
b11 6
b11 -
b11 H
b11 \
b11 b
b11000 [
b11000 )
b11000 a
1"
#70000
0"
#75000
b11100 [
b11100 )
b11100 a
1"
#80000
0"
#85000
b100000 [
b100000 )
b100000 a
1"
#90000
0"
#95000
b100100 [
b100100 )
b100100 a
1"
#100000
0"
#105000
b101000 [
b101000 )
b101000 a
1"
#110000
0"
#115000
b101100 [
b101100 )
b101100 a
1"
#120000
0"
#125000
b110000 [
b110000 )
b110000 a
1"
#130000
0"
#135000
b110100 [
b110100 )
b110100 a
1"
#140000
0"
#145000
b111000 [
b111000 )
b111000 a
1"
#150000
0"
#155000
b111100 [
b111100 )
b111100 a
1"
#160000
0"
#165000
b1000000 [
b1000000 )
b1000000 a
1"
#170000
0"
#175000
b1000100 [
b1000100 )
b1000100 a
1"
#180000
0"
#185000
b1001000 [
b1001000 )
b1001000 a
1"
#190000
0"
#195000
b1001100 [
b1001100 )
b1001100 a
1"
#200000
0"
#205000
b1010000 [
b1010000 )
b1010000 a
1"
#210000
0"
#215000
b1010100 [
b1010100 )
b1010100 a
1"
#220000
0"
#225000
b1011000 [
b1011000 )
b1011000 a
1"
#230000
0"
#235000
b1011100 [
b1011100 )
b1011100 a
1"
#240000
0"
#245000
b1100000 [
b1100000 )
b1100000 a
1"
#250000
0"
#255000
b1100100 [
b1100100 )
b1100100 a
1"
#260000
0"
#265000
b1101000 [
b1101000 )
b1101000 a
1"
#270000
0"
#275000
b1101100 [
b1101100 )
b1101100 a
1"
#280000
0"
#285000
b1110000 [
b1110000 )
b1110000 a
1"
#290000
0"
#295000
b1110100 [
b1110100 )
b1110100 a
1"
#300000
0"
#305000
b1111000 [
b1111000 )
b1111000 a
1"
#310000
0"
#315000
b1111100 [
b1111100 )
b1111100 a
1"
#320000
0"
#325000
b10000000 [
b10000000 )
b10000000 a
1"
#330000
0"
#335000
b10000100 [
b10000100 )
b10000100 a
1"
#340000
0"
#345000
b10001000 [
b10001000 )
b10001000 a
1"
#350000
0"
#355000
b10001100 [
b10001100 )
b10001100 a
1"
#360000
0"
#365000
b10010000 [
b10010000 )
b10010000 a
1"
#370000
0"
#375000
b10010100 [
b10010100 )
b10010100 a
1"
#380000
0"
#385000
b10011000 [
b10011000 )
b10011000 a
1"
#390000
0"
#395000
b10011100 [
b10011100 )
b10011100 a
1"
#400000
0"
#405000
b10100000 [
b10100000 )
b10100000 a
1"
#410000
0"
#415000
b10100100 [
b10100100 )
b10100100 a
1"
#420000
0"
#425000
b10101000 [
b10101000 )
b10101000 a
1"
#430000
0"
#435000
b10101100 [
b10101100 )
b10101100 a
1"
#440000
0"
#445000
b10110000 [
b10110000 )
b10110000 a
1"
#450000
0"
#455000
b10110100 [
b10110100 )
b10110100 a
1"
#460000
0"
#465000
b10111000 [
b10111000 )
b10111000 a
1"
#470000
0"
#475000
b10111100 [
b10111100 )
b10111100 a
1"
#480000
0"
#485000
b11000000 [
b11000000 )
b11000000 a
1"
#490000
0"
#495000
b11000100 [
b11000100 )
b11000100 a
1"
#500000
0"
#505000
b11001000 [
b11001000 )
b11001000 a
1"
#510000
0"
#515000
b11001100 [
b11001100 )
b11001100 a
1"
