src/definitions.sv
`ifndef DEFINITIONS_SV
`define DEFINITIONS_SV

// ALU control signals
`define ALU_ADD 3'b000
`define ALU_SUB 3'b001
`define ALU_AND 3'b010
`define ALU_OR  3'b011

// Opcode definitions (no JAL, only these 4 types)
`define OP_R_TYPE   7'b0110011  // ADD, SUB, AND, OR
`define OP_I_TYPE   7'b0000011  // LD  (Load Double)
`define OP_S_TYPE   7'b0100011  // SD  (Store Double)
`define OP_B_TYPE   7'b1100011  // BEQ (Branch if Equal) 

// Function codes for R‑type
`define FUNC3_ADD_SUB 3'b000
`define FUNC3_AND     3'b111
`define FUNC3_OR      3'b110

`define FUNC7_ADD     7'b0000000
`define FUNC7_SUB     7'b0100000

`endif

src/alu.sv
`include "definitions.sv"

module alu (
    input  logic [63:0] a,
    input  logic [63:0] b,
    input  logic [2:0]  alu_control,
    output logic [63:0] result,
    output logic        zero
);

    always_comb begin
        case (alu_control)
            `ALU_ADD: result = a + b;
            `ALU_SUB: result = a - b;
            `ALU_AND: result = a & b;
            `ALU_OR:  result = a | b;
            default:  result = a + b;
        endcase
    end

    assign zero = (result == 64'b0);

endmodule

reg_file_gaurav.sv
module reg_file(
    input logic clk,
    input logic rst,
    input logic[4:0] rd_addr1,
    output logic[63:0] rd_data1,
    input logic[4:0] rd_addr2,
    output logic[63:0] rd_data2,
    input logic[4:0] wr_addr,
    input logic[63:0] wr_data,
    input logic wr_enable,

    output logic[63:0] debug_output //reg 31 which is connected to output pins
);
logic [63:0] registers[31:0];

always_ff@(posedge clk or posedge rst) begin
    if(rst) begin
        for(int i=0;i<32;i++) begin
            registers[i]<=64'b0;
        end
    end
    else if(wr_enable) begin
        registers[wr_addr]<=wr_data;
    end
end

assign rd_data1=registers[rd_addr1];
assign rd_data2=registers[rd_addr2];

assign debug_output=registers[31];

endmodule

src/data_path.sv
module datapath (
    input  logic        clk,
    input  logic        rst,
    input  logic [31:0] instruction,
    input  logic [63:0] read_data_memory,
    input  logic [2:0]  alu_control,
    input  logic        reg_write,
    input  logic        alu_src,
    input  logic        mem_to_reg,

    output logic [63:0] alu_result,
    output logic [63:0] write_data_memory,
    output logic [4:0]  rd_addr,
    output logic        zero,
    output logic [63:0] debug_out  // (optional) contents of x31
);

    // Register‑file wires
    logic [63:0] rs1_data, rs2_data;
    logic [63:0] imm;
    logic [63:0] alu_b;
    logic [63:0] wb_data;

    // Decode register indices
    logic [4:0] rs1 = instruction[19:15]; 
    logic [4:0] rs2 = instruction[24:20];
    assign rd_addr = instruction[11:7];

    // Instantiate register file
    reg_file rf (
        .clk        (clk),
        .rst        (rst),
        .rd_addr1   (rs1),
        .rd_data1   (rs1_data),
        .rd_addr2   (rs2),
        .rd_data2   (rs2_data),
        .wr_addr    (rd_addr),
        .wr_data    (wb_data),
        .wr_enable  (reg_write),
        .debug_output(debug_out)
    );

    // Sign‑extended immediate (LD / BEQ)
    assign imm   = {{52{instruction[31]}}, instruction[31:20]};

    // ALU input mux: either register or immediate
    assign alu_b = (alu_src) ? imm : rs2_data;

    // Launch ALU
    alu alu_inst (
        .a           (rs1_data),
        .b           (alu_b),
        .alu_control (alu_control),
        .result      (alu_result),
        .zero        (zero)
    );

    // Data memory will write rs2_data
    assign write_data_memory = rs2_data;

    // Write‑back mux: from memory or from ALU
    assign wb_data = (mem_to_reg) ? read_data_memory : alu_result;

endmodule

src/data_mem.sv
module data_mem #(
    parameter integer mem_size = 256,
    parameter integer rom_size = 8,
    parameter string  rom_file = "programs/fibo_data.mem"
) (
    input  logic        clk,
    input  logic        rst,
    input  logic [31:0] addr,
    input  logic [63:0] wr_data,
    input  logic        wr_enable,
    input  logic        rd_enable,
    output logic [63:0] rd_data
);

    // Memory array
    reg [63:0] memory_array [0:mem_size-1];
    
    // Word address
    wire [31:0] word_addr = addr[31:3];

    // Initialize memory
    integer i;
    initial begin
        // Initialize all memory to zero
        for (i = 0; i < mem_size; i = i + 1) begin
            memory_array[i] = 64'b0;
        end
        
        // Load ROM data from file
        $display("Loading data memory from %s", rom_file);
        $readmemh(rom_file, memory_array, 0, rom_size-1);
        
        // Display loaded data
        $display("Loaded data memory:");
        for (i = 0; i < rom_size; i = i + 1) begin
            $display("  [%0d]: 0x%h (%0d)", i, memory_array[i], memory_array[i]);
        end
    end

    // Write operation
    always_ff @(posedge clk) begin
        if (wr_enable && word_addr >= rom_size && word_addr < mem_size) begin
            memory_array[word_addr] <= wr_data;
            $display("MEM WRITE: addr=%0d, data=%0d", word_addr, wr_data);
        end else if (wr_enable && word_addr < rom_size) begin
            $display("WARNING: Attempted write to ROM region at address %0d", word_addr);
        end
    end

    // Read operation - always output data
    assign rd_data = (word_addr < mem_size) ? memory_array[word_addr] : 64'b0;

endmodule

src/control_unit.sv
// File: src/control_unit.sv
`include "definitions.sv"

module control_unit (
    input  logic [6:0] opcode,
    input  logic [2:0] funct3,
    input  logic [6:0] funct7,
    output logic [2:0] alu_control,   // ALU operation select
    output logic       reg_write,     // Write to register file?
    output logic       mem_read,      // Read from data_mem?
    output logic       mem_write,     // Write to data_mem?
    output logic       mem_to_reg,    // Write-back: memory or ALU?
    output logic       alu_src,       // ALU second input = immediate?
    output logic       branch         // BEQ?
);

    always_comb begin
        // Defaults
        alu_control = `ALU_ADD;
        reg_write   = 1'b0;
        mem_read    = 1'b0;
        mem_write   = 1'b0;
        mem_to_reg  = 1'b0;
        alu_src     = 1'b0;
        branch      = 1'b0;

        // If opcode is all X's (unknown), do nothing
        if (opcode === 7'bxxxxxxx) begin
            // keep defaults; no warning
        end else begin
            case (opcode)
                // I-Type (LD)
                `OP_I_TYPE: begin
                    alu_control = `ALU_ADD;
                    reg_write   = 1'b1;
                    mem_read    = 1'b1;
                    mem_write   = 1'b0;
                    mem_to_reg  = 1'b1;
                    alu_src     = 1'b1;
                    branch      = 1'b0;
                end

                // I-Type ALU operations (ADDI, etc.)
                `OP_I_ALU: begin
                    alu_control = `ALU_ADD;
                    reg_write   = 1'b1;
                    mem_read    = 1'b0;
                    mem_write   = 1'b0;
                    mem_to_reg  = 1'b0;
                    alu_src     = 1'b1;  // Use immediate
                    branch      = 1'b0;
                end

                // S-Type (SD)
                `OP_S_TYPE: begin
                    alu_control = `ALU_ADD;
                    reg_write   = 1'b0;
                    mem_read    = 1'b0;
                    mem_write   = 1'b1;
                    mem_to_reg  = 1'b0;
                    alu_src     = 1'b1;
                    branch      = 1'b0;
                end

                // R-Type (ADD/SUB/AND/OR)
                `OP_R_TYPE: begin
                    case (funct3)
                        `FUNC3_ADD_SUB: begin
                            if (funct7 == `FUNC7_SUB)
                                alu_control = `ALU_SUB;
                            else
                                alu_control = `ALU_ADD;
                        end
                        `FUNC3_AND: alu_control = `ALU_AND;
                        `FUNC3_OR:  alu_control = `ALU_OR;
                        default:    alu_control = `ALU_ADD;
                    endcase
                    
                    reg_write   = 1'b1;
                    mem_read    = 1'b0;
                    mem_write   = 1'b0;
                    mem_to_reg  = 1'b0;
                    alu_src     = 1'b0;
                    branch      = 1'b0;
                end

                // B-Type (BEQ)
                `OP_B_TYPE: begin
                    alu_control = `ALU_SUB;  // Subtract to compare
                    reg_write   = 1'b0;      // Don't write to register
                    mem_read    = 1'b0;      // Don't access memory
                    mem_write   = 1'b0;      // Don't access memory
                    mem_to_reg  = 1'b0;      // Don't care
                    alu_src     = 1'b0;      // Use register for comparison
                    branch      = 1'b1;      // This is a branch instruction
                end

                default: begin
                    $display("Warning: Unknown opcode: 0x%h", opcode);
                end
            endcase
        end
    end

endmodule

src/sign_extend.sv
`include "definitions.sv"

module sign_extend (
    input  logic [31:0] instr,
    output logic [63:0] imm_out
);

    // Different immediate formats
    logic [63:0] imm_i, imm_s, imm_b;
    
    // I-type immediate (bits [31:20]) - for LD and ADDI
    assign imm_i = {{52{instr[31]}}, instr[31:20]};
    
    // S-type immediate (bits [31:25] + [11:7]) - for SD
    assign imm_s = {{52{instr[31]}}, instr[31:25], instr[11:7]};
    
    // B-type immediate (bits: [31], [7], [30:25], [11:8], then <<1) - for BEQ
    assign imm_b = {{51{instr[31]}}, instr[31], instr[7], instr[30:25], instr[11:8], 1'b0};

    // Fixed version - replace always_comb with direct assignments to avoid the warning
    assign imm_out = (instr[6:0] == `OP_S_TYPE) ? imm_s :
                     (instr[6:0] == `OP_B_TYPE) ? imm_b : imm_i;

endmodule

src/instr_mem.sv
module instr_mem #(
    parameter integer mem_size = 17,  // Increased from 10 to 20
    parameter string  mem_file = "programs/program.mem"
) (
    input  logic [31:0] address,
    output logic [31:0] instruction
);

    // Instruction array
    reg [31:0] memory_array [0:mem_size-1];
    
    // Initialize with NOP instructions first
    integer i;
    initial begin
        // Initialize all to NOP
        for (i = 0; i < mem_size; i = i + 1) begin
            memory_array[i] = 32'h00000013;  // NOP (addi x0, x0, 0)
        end
        
        // Load instructions from file
        $display("Loading instruction memory from %s", mem_file);
        $readmemh(mem_file, memory_array);
        
        // Display loaded instructions
        $display("Loaded instructions:");
        for (i = 0; i < mem_size && i < 20; i = i + 1) begin
            if (memory_array[i] != 32'h00000013) begin
                $display("  [%0d]: 0x%h", i, memory_array[i]);
            end
        end
    end

    // Output instruction
    wire [31:0] word_addr = address[31:2];
    assign instruction = (word_addr < mem_size) ? memory_array[word_addr] : 32'h00000013;

endmodule

src/pc_logic.sv
module pc_logic (
    input  logic        clk,
    input  logic        rst,
    input  logic        branch,
    input  logic        zero,
    input  logic [63:0] imm,
    output logic [63:0] pc
);

    logic [63:0] pc_next;
    logic        take_branch;
    
    // Branch decision: take branch if it's a branch instruction AND zero flag is set
    assign take_branch = branch & zero;
    
    // Next PC calculation
    always_comb begin
        if (take_branch) begin
            // Branch taken: PC = PC + sign_extended_offset
            pc_next = pc + imm;
        end else begin
            // Normal increment: PC = PC + 4
            pc_next = pc + 64'd4;
        end
    end

    // PC register
    always_ff @(posedge clk or posedge rst) begin
        if (rst) begin
            pc <= 64'b0;
        end else begin
            pc <= pc_next;
        end
    end

endmodule

src/single_cycle_cpu.sv
`include "definitions.sv"

module single_cycle_cpu (
    input  logic        clk,
    input  logic        rst,
    output logic [63:0] debug_out
);

    // Internal signals
    logic [63:0] pc;
    logic [31:0] instruction;
    logic [63:0] imm;

    // Control signals
    logic [2:0]  alu_control;
    logic        reg_write;
    logic        mem_read;
    logic        mem_write;
    logic        mem_to_reg;
    logic        alu_src;
    logic        branch;

    // Datapath signals
    logic [63:0] alu_result;
    logic [63:0] write_data_memory;
    logic [63:0] read_data_memory;
    logic [4:0]  rd_addr;
    logic        zero;

    // Program Counter
    pc_logic pc_inst (
        .clk    (clk),
        .rst    (rst),
        .branch (branch),
        .zero   (zero),
        .imm    (imm),
        .pc     (pc)
    );

    // Instruction Memory - now loads from file
    instr_mem #(
        .mem_size(17),
        .mem_file("programs/fibo_comp.mem")
    ) instr_mem_inst (
        .address    (pc[31:0]),
        .instruction(instruction)
    );

    // Sign Extension
    sign_extend sign_ext_inst (
        .instr   (instruction),
        .imm_out (imm)
    );

    // Control Unit
    control_unit cu_inst (
        .opcode      (instruction[6:0]),
        .funct3      (instruction[14:12]),
        .funct7      (instruction[31:25]),
        .alu_control (alu_control),
        .reg_write   (reg_write),
        .mem_read    (mem_read),
        .mem_write   (mem_write),
        .mem_to_reg  (mem_to_reg),
        .alu_src     (alu_src),
        .branch      (branch)
    );

    // Data Memory - now loads from file
    data_mem #(
        .mem_size(256),
        .rom_size(2),
        .rom_file("programs/fibo_data.mem")
    ) data_mem_inst (
        .clk       (clk),
        .rst       (rst),
        .addr      (alu_result[31:0]),
        .wr_data   (write_data_memory),
        .wr_enable (mem_write),
        .rd_enable (1'b1),
        .rd_data   (read_data_memory)
    );

    // Datapath
    datapath dp_inst (
        .clk                 (clk),
        .rst                 (rst),
        .instruction         (instruction),
        .read_data_memory    (read_data_memory),
        .alu_control         (alu_control),
        .reg_write           (reg_write),
        .alu_src             (alu_src),
        .mem_to_reg          (mem_to_reg),
        .alu_result          (alu_result),
        .write_data_memory   (write_data_memory),
        .rd_addr             (rd_addr),
        .zero                (zero),
        .debug_out           (debug_out)
    );

endmodule

testbench/tb_single_cycle_cpu.sv
`timescale 1ns/1ps

module tb_single_cycle_cpu;
    logic        clk, rst;
    logic [63:0] debug_out;

    // Instantiate CPU
    single_cycle_cpu uut (
        .clk      (clk),
        .rst      (rst),
        .debug_out(debug_out)
    );

    // Clock generation
    initial clk = 0;
    always #5 clk = ~clk;

    // Test sequence
    initial begin
        $dumpfile("waveform.vcd");
        $dumpvars(0, tb_single_cycle_cpu);

        $display("=== RISC-V Single Cycle CPU Test ===");
        $display("Loading program and data from .mem files");
        $display("Program: Load 15, Load 25, Add them, Set debug to 3");
        $display("");

        // Reset
        rst = 1;
        #20;
        rst = 0;
        $display("Reset released, starting execution...");
        $display("");

        // Run for several cycles
        #100;
        
        // Check final results
        $display("=== FINAL RESULTS ===");
        $display("Debug output (Register 31): %0d", debug_out);
        $display("Register 1: %0d", uut.dp_inst.rf.registers[1]);
        $display("Register 2: %0d", uut.dp_inst.rf.registers[2]);
        $display("Register 3: %0d", uut.dp_inst.rf.registers[3]);
        
        if (debug_out == 64'd3) begin
            $display("✓ SUCCESS: Debug register correct!");
        end else begin
            $display("✗ FAILURE: Debug register wrong, expected 3, got %0d", debug_out);
        end
        
        if (uut.dp_inst.rf.registers[3] == 64'd40) begin
            $display("✓ SUCCESS: Addition correct! 15 + 25 = 40");
        end else begin
            $display("✗ FAILURE: Addition wrong, expected 40, got %0d", uut.dp_inst.rf.registers[3]);
        end
        
        $display("\n=== PROGRAM VERIFICATION ===");
        $display("Expected execution:");
        $display("1. LD x1, 0(x0)    -> x1 = 15");
        $display("2. LD x2, 8(x0)    -> x2 = 25");
        $display("3. ADD x3, x1, x2  -> x3 = 40");
        $display("4. ADDI x31, x0, 3 -> x31 = 3");
        
        $finish;
    end

    // Simple monitoring
    always @(posedge clk) begin
        if (!rst) begin
            $display("Cycle | PC: 0x%02h | Instr: 0x%h | R1: %0d | R2: %0d | R3: %0d | R31: %0d", 
                     uut.pc[7:0], uut.instruction,
                     uut.dp_inst.rf.registers[1],
                     uut.dp_inst.rf.registers[2], 
                     uut.dp_inst.rf.registers[3],
                     uut.dp_inst.rf.registers[31]);
        end
    end

endmodule

waveform.vcd
$date
	Tue Jun 10 11:08:35 2025
$end
$version
	Icarus Verilog
$end
$timescale
	1ps
$end
$scope module tb_single_cycle_cpu $end
$var wire 64 ! debug_out [63:0] $end
$var reg 1 " clk $end
$var reg 1 # rst $end
$scope module uut $end
$var wire 1 " clk $end
$var wire 1 # rst $end
$var wire 1 $ zero $end
$var wire 64 % write_data_memory [63:0] $end
$var wire 1 & reg_write $end
$var wire 64 ' read_data_memory [63:0] $end
$var wire 5 ( rd_addr [4:0] $end
$var wire 64 ) pc [63:0] $end
$var wire 1 * mem_write $end
$var wire 1 + mem_to_reg $end
$var wire 1 , mem_read $end
$var wire 32 - instruction [31:0] $end
$var wire 64 . imm [63:0] $end
$var wire 64 / debug_out [63:0] $end
$var wire 1 0 branch $end
$var wire 1 1 alu_src $end
$var wire 64 2 alu_result [63:0] $end
$var wire 3 3 alu_control [2:0] $end
$scope module cu_inst $end
$var wire 3 4 funct3 [2:0] $end
$var wire 7 5 funct7 [6:0] $end
$var wire 7 6 opcode [6:0] $end
$var reg 3 7 alu_control [2:0] $end
$var reg 1 1 alu_src $end
$var reg 1 0 branch $end
$var reg 1 , mem_read $end
$var reg 1 + mem_to_reg $end
$var reg 1 * mem_write $end
$var reg 1 & reg_write $end
$upscope $end
$scope module data_mem_inst $end
$var wire 32 8 addr [31:0] $end
$var wire 1 " clk $end
$var wire 1 9 rd_enable $end
$var wire 1 # rst $end
$var wire 1 * wr_enable $end
$var wire 64 : wr_data [63:0] $end
$var wire 32 ; word_addr [31:0] $end
$var wire 64 < rd_data [63:0] $end
$var parameter 32 = mem_size $end
$var parameter 136 > rom_file $end
$var parameter 32 ? rom_size $end
$var integer 32 @ i [31:0] $end
$upscope $end
$scope module dp_inst $end
$var wire 3 A alu_control [2:0] $end
$var wire 1 1 alu_src $end
$var wire 1 " clk $end
$var wire 1 + mem_to_reg $end
$var wire 64 B read_data_memory [63:0] $end
$var wire 1 & reg_write $end
$var wire 1 # rst $end
$var wire 64 C write_data_memory [63:0] $end
$var wire 1 $ zero $end
$var wire 64 D wb_data [63:0] $end
$var wire 64 E rs2_data [63:0] $end
$var wire 5 F rs2 [4:0] $end
$var wire 64 G rs1_data [63:0] $end
$var wire 5 H rs1 [4:0] $end
$var wire 5 I rd_addr [4:0] $end
$var wire 32 J instruction [31:0] $end
$var wire 64 K imm [63:0] $end
$var wire 64 L debug_out [63:0] $end
$var wire 64 M alu_result [63:0] $end
$var wire 64 N alu_b [63:0] $end
$scope module alu_inst $end
$var wire 3 O alu_control [2:0] $end
$var wire 64 P b [63:0] $end
$var wire 1 $ zero $end
$var wire 64 Q a [63:0] $end
$var reg 64 R result [63:0] $end
$upscope $end
$scope module rf $end
$var wire 1 " clk $end
$var wire 64 S debug_output [63:0] $end
$var wire 5 T rd_addr1 [4:0] $end
$var wire 5 U rd_addr2 [4:0] $end
$var wire 1 # rst $end
$var wire 5 V wr_addr [4:0] $end
$var wire 64 W wr_data [63:0] $end
$var wire 1 & wr_enable $end
$var wire 64 X rd_data2 [63:0] $end
$var wire 64 Y rd_data1 [63:0] $end
$var integer 32 Z i [31:0] $end
$upscope $end
$upscope $end
$scope module instr_mem_inst $end
$var wire 32 [ address [31:0] $end
$var wire 32 \ word_addr [31:0] $end
$var wire 32 ] instruction [31:0] $end
$var parameter 160 ^ mem_file $end
$var parameter 32 _ mem_size $end
$var integer 32 ` i [31:0] $end
$upscope $end
$scope module pc_inst $end
$var wire 1 0 branch $end
$var wire 1 " clk $end
$var wire 1 # rst $end
$var wire 1 a take_branch $end
$var wire 1 $ zero $end
$var wire 64 b imm [63:0] $end
$var reg 64 c pc [63:0] $end
$var reg 64 d pc_next [63:0] $end
$upscope $end
$scope module sign_ext_inst $end
$var wire 32 e instr [31:0] $end
$var wire 64 f imm_s [63:0] $end
$var wire 64 g imm_i [63:0] $end
$var wire 64 h imm_b [63:0] $end
$var reg 64 i imm_out [63:0] $end
$upscope $end
$upscope $end
$upscope $end
$enddefinitions $end
$comment Show the parameter values. $end
$dumpall
b101 _
b111000001110010011011110110011101110010011000010110110101110011001011110111000001110010011011110110011101110010011000010110110100101110011011010110010101101101 ^
b1000 ?
b111000001110010011011110110011101110010011000010110110101110011001011110110010001100001011101000110000100101110011011010110010101101101 >
b100000000 =
$end
#0
$dumpvars
b0 i
b100000000000 h
b0 g
b1 f
b11000010000011 e
b100 d
b0 c
b0 b
0a
b101 `
b11000010000011 ]
b0 \
b0 [
b100000 Z
b0 Y
b0 X
b1111 W
b1 V
b0 U
b0 T
b0 S
b0 R
b0 Q
b0 P
b0 O
b0 N
b0 M
b0 L
b0 K
b11000010000011 J
b1 I
b0 H
b0 G
b0 F
b0 E
b1111 D
b0 C
b1111 B
b0 A
b1000 @
b1111 <
b0 ;
b0 :
19
b0 8
b0 7
b11 6
b0 5
b11 4
b0 3
b0 2
11
00
b0 /
b0 .
b11000010000011 -
1,
1+
0*
b0 )
b1 (
b1111 '
1&
b0 %
1$
1#
0"
b0 !
$end
#5000
b100000 Z
1"
#10000
0"
#15000
b100000 Z
1"
#20000
0"
0#
#25000
b11001 D
b11001 W
b11001 '
b11001 <
b11001 B
b1 ;
b1000 8
0$
b1000 2
b1000 M
b1000 R
b1000 .
b1000 b
b1000 i
b1000 N
b1000 P
b1000 g
b10 f
b10 h
b1000 K
b10 (
b10 I
b10 V
b1000 F
b1000 U
b100000000011000100000011 -
b100000000011000100000011 J
b100000000011000100000011 ]
b100000000011000100000011 e
b1 \
b1000 d
b100 [
b100 )
b100 c
1"
#30000
0"
#35000
b0 '
b0 <
b0 B
b101 ;
b101000 8
b101000 2
b101000 M
b101000 R
b101000 D
b101000 W
b10 .
b10 b
b10 i
b11001 N
b11001 P
b11001 %
b11001 :
b11001 C
b11001 E
b11001 X
b1111 G
b1111 Q
b1111 Y
01
0+
0,
1&
b10 g
b11 f
b100000000010 h
b10 K
b11 (
b11 I
b11 V
b10 F
b10 U
b1 H
b1 T
b0 4
b110011 6
b1000001000000110110011 -
b1000001000000110110011 J
b1000001000000110110011 ]
b1000001000000110110011 e
b10 \
b1100 d
b1000 [
b1000 )
b1000 c
1"
#40000
0"
#45000
b1111 '
b1111 <
b1111 B
b0 ;
b11 D
b11 W
b11 8
b11 2
b11 M
b11 R
b11 N
b11 P
b11 .
b11 b
b11 i
b101000 %
b101000 :
b101000 C
b101000 E
b101000 X
b0 G
b0 Q
b0 Y
11
1&
b11 g
b11111 f
b100000011110 h
b11 K
b11111 (
b11111 I
b11111 V
b11 F
b11 U
b0 H
b0 T
b10011 6
b1100000000111110010011 -
b1100000000111110010011 J
b1100000000111110010011 ]
b1100000000111110010011 e
b11 \
b10000 d
b1100 [
b1100 )
b1100 c
1"
#50000
0"
#55000
b0 D
b0 W
b0 8
1$
b0 2
b0 M
b0 R
b0 .
b0 b
b0 i
b0 N
b0 P
b0 %
b0 :
b0 C
b0 E
b0 X
b0 g
b0 f
b0 h
b0 K
b0 (
b0 I
b0 V
b0 F
b0 U
b10011 -
b10011 J
b10011 ]
b10011 e
b100 \
b10100 d
b10000 [
b11 !
b11 /
b11 L
b11 S
b10000 )
b10000 c
1"
#60000
0"
#65000
b101 \
b11000 d
b10100 [
b10100 )
b10100 c
1"
#70000
0"
#75000
b110 \
b11100 d
b11000 [
b11000 )
b11000 c
1"
#80000
0"
#85000
b111 \
b100000 d
b11100 [
b11100 )
b11100 c
1"
#90000
0"
#95000
b1000 \
b100100 d
b100000 [
b100000 )
b100000 c
1"
#100000
0"
#105000
b1001 \
b101000 d
b100100 [
b100100 )
b100100 c
1"
#110000
0"
#115000
b1010 \
b101100 d
b101000 [
b101000 )
b101000 c
1"
