src/definitions.sv
`ifndef DEFINITIONS_SV
`define DEFINITIONS_SV

// ALU control signals
`define ALU_ADD 3'b000
`define ALU_SUB 3'b001
`define ALU_AND 3'b010
`define ALU_OR  3'b011

// Opcode definitions (no JAL, only these 4 types)
`define OP_R_TYPE   7'b0110011  // ADD, SUB, AND, OR
`define OP_I_TYPE   7'b0000011  // LD  (Load Double)
`define OP_S_TYPE   7'b0100011  // SD  (Store Double)
`define OP_B_TYPE   7'b1100011  // BEQ (Branch if Equal) 

// Function codes for R‑type
`define FUNC3_ADD_SUB 3'b000
`define FUNC3_AND     3'b111
`define FUNC3_OR      3'b110

`define FUNC7_ADD     7'b0000000
`define FUNC7_SUB     7'b0100000

`endif

src/alu.sv
`include "definitions.sv"

module alu (
    input  logic [63:0] a,
    input  logic [63:0] b,
    input  logic [2:0]  alu_control,
    output logic [63:0] result,
    output logic        zero
);

    always_comb begin
        case (alu_control)
            `ALU_ADD: result = a + b;
            `ALU_SUB: result = a - b;
            `ALU_AND: result = a & b;
            `ALU_OR:  result = a | b;
            default:  result = a + b;
        endcase
    end

    assign zero = (result == 64'b0);

endmodule

reg_file_gaurav.sv
module reg_file(
    input logic clk,
    input logic rst,
    input logic[4:0] rd_addr1,
    output logic[63:0] rd_data1,
    input logic[4:0] rd_addr2,
    output logic[63:0] rd_data2,
    input logic[4:0] wr_addr,
    input logic[63:0] wr_data,
    input logic wr_enable,

    output logic[63:0] debug_output //reg 31 which is connected to output pins
);
logic [63:0] registers[31:0];

always_ff@(posedge clk or posedge rst) begin
    if(rst) begin
        for(int i=0;i<32;i++) begin
            registers[i]<=64'b0;
        end
    end
    else if(wr_enable) begin
        registers[wr_addr]<=wr_data;
    end
end

assign rd_data1=registers[rd_addr1];
assign rd_data2=registers[rd_addr2];

assign debug_output=registers[31];

endmodule

src/data_path.sv
module datapath (
    input  logic        clk,
    input  logic        rst,
    input  logic [31:0] instruction,
    input  logic [63:0] read_data_memory,
    input  logic [2:0]  alu_control,
    input  logic        reg_write,
    input  logic        alu_src,
    input  logic        mem_to_reg,

    output logic [63:0] alu_result,
    output logic [63:0] write_data_memory,
    output logic [4:0]  rd_addr,
    output logic        zero,
    output logic [63:0] debug_out
);

    // Internal signals
    logic [63:0] rs1_data, rs2_data;
    logic [63:0] imm;
    logic [63:0] alu_b;
    logic [63:0] wb_data;

    // Extract register addresses
    wire [4:0] rs1 = instruction[19:15];
    wire [4:0] rs2 = instruction[24:20];
    assign rd_addr = instruction[11:7];

    // Sign extend immediate (I-type)
    assign imm = {{52{instruction[31]}}, instruction[31:20]};

    // Register file
    reg_file rf (
        .clk        (clk),
        .rst        (rst),
        .rd_addr1   (rs1),
        .rd_data1   (rs1_data),
        .rd_addr2   (rs2),
        .rd_data2   (rs2_data),
        .wr_addr    (rd_addr),
        .wr_data    (wb_data),
        .wr_enable  (reg_write),
        .debug_output(debug_out)
    );

    // ALU input mux
    assign alu_b = alu_src ? imm : rs2_data;

    // ALU
    alu alu_inst (
        .a           (rs1_data),
        .b           (alu_b),
        .alu_control (alu_control),
        .result      (alu_result),
        .zero        (zero)
    );

    // Memory write data
    assign write_data_memory = rs2_data;

    // Write-back mux
    assign wb_data = mem_to_reg ? read_data_memory : alu_result;

endmodule

src/data_mem.sv
module data_mem #(
    parameter integer mem_size = 256,
    parameter integer rom_size = 8
) (
    input  logic        clk,
    input  logic        rst,
    input  logic [31:0] addr,
    input  logic [63:0] wr_data,
    input  logic        wr_enable,
    input  logic        rd_enable,
    output logic [63:0] rd_data
);

    // Memory array
    reg [63:0] memory_array [0:mem_size-1];
    
    // Word address
    wire [31:0] word_addr = addr[31:3];

    // Initialize memory
    integer i;
    initial begin
        for (i = 0; i < mem_size; i = i + 1) begin
            memory_array[i] = 64'b0;
        end
        
        // Set test data
        memory_array[0] = 64'd15;  // Address 0: value 15
        memory_array[1] = 64'd25;  // Address 8: value 25
        
        $display("Memory initialized: [0]=%0d, [1]=%0d", memory_array[0], memory_array[1]);
    end

    // Write operation
    always_ff @(posedge clk) begin
        if (wr_enable && word_addr < mem_size) begin
            memory_array[word_addr] <= wr_data;
            $display("MEM WRITE: addr=%0d, data=%0d", word_addr, wr_data);
        end
    end

    // Read operation - always output data
    assign rd_data = (word_addr < mem_size) ? memory_array[word_addr] : 64'b0;

endmodule

src/control_unit.sv
// File: src/control_unit.sv
`include "definitions.sv"

module control_unit (
    input  logic [6:0] opcode,
    input  logic [2:0] funct3,
    input  logic [6:0] funct7,
    output logic [2:0] alu_control,   // ALU operation select
    output logic       reg_write,     // Write to register file?
    output logic       mem_read,      // Read from data_mem?
    output logic       mem_write,     // Write to data_mem?
    output logic       mem_to_reg,    // Write-back: memory or ALU?
    output logic       alu_src,       // ALU second input = immediate?
    output logic       branch         // BEQ?
);

    always_comb begin
        // Defaults
        alu_control = `ALU_ADD;
        reg_write   = 1'b0;
        mem_read    = 1'b0;
        mem_write   = 1'b0;
        mem_to_reg  = 1'b0;
        alu_src     = 1'b0;
        branch      = 1'b0;

        // If opcode is all X's (unknown), do nothing
        if (opcode === 7'bxxxxxxx) begin
            // keep defaults; no warning
        end else begin
            case (opcode)
                // I-Type (LD)
                `OP_I_TYPE: begin
                    alu_control = `ALU_ADD;
                    reg_write   = 1'b1;
                    mem_read    = 1'b1;
                    mem_write   = 1'b0;
                    mem_to_reg  = 1'b1;
                    alu_src     = 1'b1;
                    branch      = 1'b0;
                end

                // I-Type ALU operations (ADDI, etc.)
                `OP_I_ALU: begin
                    alu_control = `ALU_ADD;
                    reg_write   = 1'b1;
                    mem_read    = 1'b0;
                    mem_write   = 1'b0;
                    mem_to_reg  = 1'b0;
                    alu_src     = 1'b1;  // Use immediate
                    branch      = 1'b0;
                end

                // S-Type (SD)
                `OP_S_TYPE: begin
                    alu_control = `ALU_ADD;
                    reg_write   = 1'b0;
                    mem_read    = 1'b0;
                    mem_write   = 1'b1;
                    mem_to_reg  = 1'b0;
                    alu_src     = 1'b1;
                    branch      = 1'b0;
                end

                // R-Type (ADD/SUB/AND/OR)
                `OP_R_TYPE: begin
                    alu_control = `ALU_ADD;
                    reg_write   = 1'b1;
                    mem_read    = 1'b0;
                    mem_write   = 1'b0;
                    mem_to_reg  = 1'b0;
                    alu_src     = 1'b0;
                    branch      = 1'b0;
                end

                // B-Type (BEQ)
                `OP_B_TYPE: begin
                    alu_control = `ALU_SUB;
                    reg_write   = 1'b0;
                    mem_read    = 1'b0;
                    mem_write   = 1'b0;
                    mem_to_reg  = 1'b0;
                    alu_src     = 1'b0;
                    branch      = 1'b1;
                end

                default: begin
                    $display("Warning: Unknown opcode: 0x%h", opcode);
                end
            endcase
        end
    end

endmodule

src/sign_extend.sv
`include "definitions.sv"

module sign_extend (
    input  logic [31:0] instr,
    output logic [63:0] imm_out
);

    // Simple I-type immediate for all instructions
    assign imm_out = {{52{instr[31]}}, instr[31:20]};

endmodule

src/instr_mem.sv
module instr_mem #(
    parameter integer mem_size = 5
) (
    input  logic [31:0] address,
    output logic [31:0] instruction
);

    // Instruction array
    reg [31:0] memory_array [0:mem_size-1];
    
    // Initialize with our test program
    initial begin
        memory_array[0] = 32'h00003083;  // ld x1, 0(x0)   - Load 15 into x1
        memory_array[1] = 32'h00803103;  // ld x2, 8(x0)   - Load 25 into x2
        memory_array[2] = 32'h002081b3;  // add x3, x1, x2 - x3 = x1 + x2 = 40
        memory_array[3] = 32'h00300f93;  // addi x31, x0, 3 - x31 = 3
        memory_array[4] = 32'h00000013;  // nop
        
        $display("Instructions loaded:");
        $display("  [0]: 0x%h (ld x1, 0(x0))", memory_array[0]);
        $display("  [1]: 0x%h (ld x2, 8(x0))", memory_array[1]);
        $display("  [2]: 0x%h (add x3, x1, x2)", memory_array[2]);
        $display("  [3]: 0x%h (addi x31, x0, 3)", memory_array[3]);
    end

    // Output instruction
    wire [31:0] word_addr = address[31:2];
    assign instruction = (word_addr < mem_size) ? memory_array[word_addr] : 32'h00000013;

endmodule

src/pc_logic.sv
module pc_logic (
    input  logic        clk,
    input  logic        rst,
    input  logic        branch,
    input  logic        zero,
    input  logic [63:0] imm,
    output logic [63:0] pc
);

    always_ff @(posedge clk or posedge rst) begin
        if (rst) begin
            pc <= 64'b0;
        end else begin
            pc <= pc + 64'd4;  // Simple increment, ignore branches for now
        end
    end

endmodule

src/single_cycle_cpu.sv
`include "definitions.sv"

module single_cycle_cpu (
    input  logic        clk,
    input  logic        rst,
    output logic [63:0] debug_out
);

    // Internal signals
    logic [63:0] pc;
    logic [31:0] instruction;
    logic [63:0] imm;

    // Control signals
    logic [2:0]  alu_control;
    logic        reg_write;
    logic        mem_read;
    logic        mem_write;
    logic        mem_to_reg;
    logic        alu_src;
    logic        branch;

    // Datapath signals
    logic [63:0] alu_result;
    logic [63:0] write_data_memory;
    logic [63:0] read_data_memory;
    logic [4:0]  rd_addr;
    logic        zero;

    // Program Counter
    pc_logic pc_inst (
        .clk    (clk),
        .rst    (rst),
        .branch (branch),
        .zero   (zero),
        .imm    (imm),
        .pc     (pc)
    );

    // Instruction Memory
    instr_mem #(.mem_size(5)) instr_mem_inst (
        .address    (pc[31:0]),
        .instruction(instruction)
    );

    // Sign Extension
    sign_extend sign_ext_inst (
        .instr   (instruction),
        .imm_out (imm)
    );

    // Control Unit
    control_unit cu_inst (
        .opcode      (instruction[6:0]),
        .funct3      (instruction[14:12]),
        .funct7      (instruction[31:25]),
        .alu_control (alu_control),
        .reg_write   (reg_write),
        .mem_read    (mem_read),
        .mem_write   (mem_write),
        .mem_to_reg  (mem_to_reg),
        .alu_src     (alu_src),
        .branch      (branch)
    );

    // Data Memory
    data_mem #(.mem_size(256), .rom_size(8)) data_mem_inst (
        .clk       (clk),
        .rst       (rst),
        .addr      (alu_result[31:0]),
        .wr_data   (write_data_memory),
        .wr_enable (mem_write),
        .rd_enable (1'b1),
        .rd_data   (read_data_memory)
    );

    // Datapath
    datapath dp_inst (
        .clk                 (clk),
        .rst                 (rst),
        .instruction         (instruction),
        .read_data_memory    (read_data_memory),
        .alu_control         (alu_control),
        .reg_write           (reg_write),
        .alu_src             (alu_src),
        .mem_to_reg          (mem_to_reg),
        .alu_result          (alu_result),
        .write_data_memory   (write_data_memory),
        .rd_addr             (rd_addr),
        .zero                (zero),
        .debug_out           (debug_out)
    );

endmodule

testbench/tb_single_cycle_cpu.sv
`timescale 1ns/1ps

module tb_single_cycle_cpu;
    logic        clk, rst;
    logic [63:0] debug_out;

    // Instantiate CPU
    single_cycle_cpu uut (
        .clk      (clk),
        .rst      (rst),
        .debug_out(debug_out)
    );

    // Clock generation
    initial clk = 0;
    always #5 clk = ~clk;

    // Test sequence
    initial begin
        $dumpfile("waveform.vcd");
        $dumpvars(0, tb_single_cycle_cpu);

        $display("=== RISC-V Single Cycle CPU Test ===");
        $display("Program: Load 15, Load 25, Add them, Set debug to 3");
        $display("");

        // Reset
        rst = 1;
        #20;
        rst = 0;
        $display("Reset released, starting execution...");
        $display("");

        // Run for several cycles
        #100;
        
        // Check final results
        $display("=== FINAL RESULTS ===");
        $display("Debug output (Register 31): %0d", debug_out);
        $display("Register 1: %0d", uut.dp_inst.rf.registers[1]);
        $display("Register 2: %0d", uut.dp_inst.rf.registers[2]);
        $display("Register 3: %0d", uut.dp_inst.rf.registers[3]);
        
        if (debug_out == 64'd3) begin
            $display("✓ SUCCESS: Debug register correct!");
        end else begin
            $display("✗ FAILURE: Debug register wrong");
        end
        
        if (uut.dp_inst.rf.registers[3] == 64'd40) begin
            $display("✓ SUCCESS: Addition correct! 15 + 25 = 40");
        end else begin
            $display("✗ FAILURE: Addition wrong");
        end
        
        $finish;
    end

    // Simple monitoring
    always @(posedge clk) begin
        if (!rst) begin
            $display("Cycle | PC: 0x%02h | Instr: 0x%h | R1: %0d | R2: %0d | R3: %0d | R31: %0d", 
                     uut.pc[7:0], uut.instruction,
                     uut.dp_inst.rf.registers[1],
                     uut.dp_inst.rf.registers[2], 
                     uut.dp_inst.rf.registers[3],
                     uut.dp_inst.rf.registers[31]);
        end
    end

endmodule

waveform.vcd
$date
	Tue Jun 10 10:19:04 2025
$end
$version
	Icarus Verilog
$end
$timescale
	1ps
$end
$scope module tb_single_cycle_cpu $end
$var wire 64 ! debug_out [63:0] $end
$var reg 1 " clk $end
$var reg 1 # rst $end
$scope module uut $end
$var wire 1 " clk $end
$var wire 1 # rst $end
$var wire 1 $ zero $end
$var wire 64 % write_data_memory [63:0] $end
$var wire 1 & reg_write $end
$var wire 64 ' read_data_memory [63:0] $end
$var wire 5 ( rd_addr [4:0] $end
$var wire 64 ) pc [63:0] $end
$var wire 1 * mem_write $end
$var wire 1 + mem_to_reg $end
$var wire 1 , mem_read $end
$var wire 32 - instruction [31:0] $end
$var wire 64 . imm [63:0] $end
$var wire 64 / debug_out [63:0] $end
$var wire 1 0 branch $end
$var wire 1 1 alu_src $end
$var wire 64 2 alu_result [63:0] $end
$var wire 3 3 alu_control [2:0] $end
$scope module cu_inst $end
$var wire 3 4 funct3 [2:0] $end
$var wire 7 5 funct7 [6:0] $end
$var wire 7 6 opcode [6:0] $end
$var reg 3 7 alu_control [2:0] $end
$var reg 1 1 alu_src $end
$var reg 1 0 branch $end
$var reg 1 , mem_read $end
$var reg 1 + mem_to_reg $end
$var reg 1 * mem_write $end
$var reg 1 & reg_write $end
$upscope $end
$scope module data_mem_inst $end
$var wire 32 8 addr [31:0] $end
$var wire 1 " clk $end
$var wire 1 9 rd_enable $end
$var wire 1 # rst $end
$var wire 1 * wr_enable $end
$var wire 64 : wr_data [63:0] $end
$var wire 32 ; word_addr [31:0] $end
$var wire 64 < rd_data [63:0] $end
$var parameter 32 = mem_size $end
$var parameter 32 > rom_size $end
$var integer 32 ? i [31:0] $end
$upscope $end
$scope module dp_inst $end
$var wire 3 @ alu_control [2:0] $end
$var wire 1 1 alu_src $end
$var wire 1 " clk $end
$var wire 1 + mem_to_reg $end
$var wire 64 A read_data_memory [63:0] $end
$var wire 1 & reg_write $end
$var wire 1 # rst $end
$var wire 64 B write_data_memory [63:0] $end
$var wire 1 $ zero $end
$var wire 64 C wb_data [63:0] $end
$var wire 64 D rs2_data [63:0] $end
$var wire 5 E rs2 [4:0] $end
$var wire 64 F rs1_data [63:0] $end
$var wire 5 G rs1 [4:0] $end
$var wire 5 H rd_addr [4:0] $end
$var wire 32 I instruction [31:0] $end
$var wire 64 J imm [63:0] $end
$var wire 64 K debug_out [63:0] $end
$var wire 64 L alu_result [63:0] $end
$var wire 64 M alu_b [63:0] $end
$scope module alu_inst $end
$var wire 3 N alu_control [2:0] $end
$var wire 64 O b [63:0] $end
$var wire 1 $ zero $end
$var wire 64 P a [63:0] $end
$var reg 64 Q result [63:0] $end
$upscope $end
$scope module rf $end
$var wire 1 " clk $end
$var wire 64 R debug_output [63:0] $end
$var wire 5 S rd_addr1 [4:0] $end
$var wire 5 T rd_addr2 [4:0] $end
$var wire 1 # rst $end
$var wire 5 U wr_addr [4:0] $end
$var wire 64 V wr_data [63:0] $end
$var wire 1 & wr_enable $end
$var wire 64 W rd_data2 [63:0] $end
$var wire 64 X rd_data1 [63:0] $end
$var integer 32 Y i [31:0] $end
$upscope $end
$upscope $end
$scope module instr_mem_inst $end
$var wire 32 Z address [31:0] $end
$var wire 32 [ word_addr [31:0] $end
$var wire 32 \ instruction [31:0] $end
$var parameter 32 ] mem_size $end
$upscope $end
$scope module pc_inst $end
$var wire 1 0 branch $end
$var wire 1 " clk $end
$var wire 1 # rst $end
$var wire 1 $ zero $end
$var wire 64 ^ imm [63:0] $end
$var reg 64 _ pc [63:0] $end
$upscope $end
$scope module sign_ext_inst $end
$var wire 32 ` instr [31:0] $end
$var wire 64 a imm_out [63:0] $end
$upscope $end
$upscope $end
$upscope $end
$enddefinitions $end
$comment Show the parameter values. $end
$dumpall
b101 ]
b1000 >
b100000000 =
$end
#0
$dumpvars
b0 a
b11000010000011 `
b0 _
b0 ^
b11000010000011 \
b0 [
b0 Z
b100000 Y
b0 X
b0 W
b1111 V
b1 U
b0 T
b0 S
b0 R
b0 Q
b0 P
b0 O
b0 N
b0 M
b0 L
b0 K
b0 J
b11000010000011 I
b1 H
b0 G
b0 F
b0 E
b0 D
b1111 C
b0 B
b1111 A
b0 @
b100000000 ?
b1111 <
b0 ;
b0 :
19
b0 8
b0 7
b11 6
b0 5
b11 4
b0 3
b0 2
11
00
b0 /
b0 .
b11000010000011 -
1,
1+
0*
b0 )
b1 (
b1111 '
1&
b0 %
1$
1#
0"
b0 !
$end
#5000
b100000 Y
1"
#10000
0"
#15000
b100000 Y
1"
#20000
0"
0#
#25000
b11001 C
b11001 V
b11001 '
b11001 <
b11001 A
b1 ;
b1000 8
0$
b1000 2
b1000 L
b1000 Q
b1000 M
b1000 O
b1000 .
b1000 ^
b1000 a
b1000 J
b10 (
b10 H
b10 U
b1000 E
b1000 T
b100000000011000100000011 -
b100000000011000100000011 I
b100000000011000100000011 \
b100000000011000100000011 `
b1 [
b100 Z
b100 )
b100 _
1"
#30000
0"
#35000
b0 '
b0 <
b0 A
b101 ;
b101000 8
b101000 2
b101000 L
b101000 Q
b101000 C
b101000 V
b11001 M
b11001 O
b11001 %
b11001 :
b11001 B
b11001 D
b11001 W
b1111 F
b1111 P
b1111 X
01
0+
0,
1&
b10 .
b10 ^
b10 a
b10 J
b11 (
b11 H
b11 U
b10 E
b10 T
b1 G
b1 S
b0 4
b110011 6
b1000001000000110110011 -
b1000001000000110110011 I
b1000001000000110110011 \
b1000001000000110110011 `
b10 [
b1000 Z
b1000 )
b1000 _
1"
#40000
0"
#45000
b1111 '
b1111 <
b1111 A
b0 ;
b11 C
b11 V
b11 8
b11 2
b11 L
b11 Q
b11 M
b11 O
b101000 %
b101000 :
b101000 B
b101000 D
b101000 W
b0 F
b0 P
b0 X
11
1&
b11 .
b11 ^
b11 a
b11 J
b11111 (
b11111 H
b11111 U
b11 E
b11 T
b0 G
b0 S
b10011 6
b1100000000111110010011 -
b1100000000111110010011 I
b1100000000111110010011 \
b1100000000111110010011 `
b11 [
b1100 Z
b1100 )
b1100 _
1"
#50000
0"
#55000
b0 C
b0 V
b0 8
1$
b0 2
b0 L
b0 Q
b0 M
b0 O
b0 %
b0 :
b0 B
b0 D
b0 W
b0 .
b0 ^
b0 a
b0 J
b0 (
b0 H
b0 U
b0 E
b0 T
b10011 -
b10011 I
b10011 \
b10011 `
b100 [
b10000 Z
b11 !
b11 /
b11 K
b11 R
b10000 )
b10000 _
1"
#60000
0"
#65000
b101 [
b10100 Z
b10100 )
b10100 _
1"
#70000
0"
#75000
b110 [
b11000 Z
b11000 )
b11000 _
1"
#80000
0"
#85000
b111 [
b11100 Z
b11100 )
b11100 _
1"
#90000
0"
#95000
b1000 [
b100000 Z
b100000 )
b100000 _
1"
#100000
0"
#105000
b1001 [
b100100 Z
b100100 )
b100100 _
1"
#110000
0"
#115000
b1010 [
b101000 Z
b101000 )
b101000 _
1"
