src/reg_file.sv
module reg_file(
    input logic clk,
    input logic rst,
    input logic[4:0] rd_addr1,
    output logic[63:0] rd_data1,
    input logic[4:0] rd_addr2,
    output logic[63:0] rd_data2,
    input logic[4:0] wr_addr,
    input logic[63:0] wr_data,
    input logic wr_enable,

    output logic[63:0] debug_output //reg 31 which is connected to output pins
);
logic [63:0] registers[31:0];

always_ff@(posedge clk or posedge rst) begin
    if(rst) begin
        for(int i=0;i<32;i++) begin
            registers[i]<=64'b0;
        end
    end
    else if(wr_enable) begin
        registers[wr_addr]<=wr_data;
    end
end

assign rd_data1=registers[rd_addr1];
assign rd_data2=registers[rd_addr2];

assign debug_output=registers[31];

endmodule

src/reg_file_tb.sv
module tb_reg_file;
    logic clk;
    logic rst;
    logic[4:0] rd_addr1;
    logic[63:0] rd_data1;
    logic[4:0] rd_addr2;
    logic[63:0] rd_data2;
    logic[4:0] wr_addr;
    logic[63:0] wr_data;
    logic wr_enable;
    logic[63:0] debug_output;

    //instantiate module
    reg_file dut(
        .clk(clk),
        .rst(rst),
        .rd_addr1(rd_addr1),
        .rd_data1(rd_data1),
        .rd_addr2(rd_addr2),
        .rd_data2(rd_data2),
        .wr_addr(wr_addr),
        .wr_data(wr_data),
        .wr_enable(wr_enable),
        .debug_output(debug_output)
    );

    //clock
    always #5 clk=~clk; //time period is 10

    initial begin
        $dumpfile("wave.vcd"); //for gtkwave
        $dumpvars(0,tb_reg_file);
        
        $display("Test register file \n");
        clk=0;
        rst=1; //apply reset
        rd_addr1=0;
        rd_addr2=0;
        wr_addr=0;
        wr_data=0;
        wr_enable=0;

        #20;
        rst=0;
        #10;

        $display("Checking initial state after reset \n");
        rd_addr1=5'b0; //register 0 and 1
        rd_addr2=5'b1;

        #10;
        $display("Register 0 = 0x%h (supposed to be 0) \n",rd_data1);
        $display("Register 1 = 0x%h (supposed to be 0) \n",rd_data2);

        $display("Checking write \n");
        //lets write to register 5
        wr_addr=5'b00101;
        wr_data=64'h0123456789ABCDEF;
        wr_enable=1;
        #10 //waiting for clock edge
        wr_enable=0;

        //let us now read from reg 5
        rd_addr1=5'b00101;
        #10
        $display("Value in register 5 : 0x%h(supposed to be 0123456789ABCDEF) \n",rd_data1);

        $display("Testing write and read from multiple registers \n");
        wr_addr=5'b01010; //reg 10
        wr_data=64'h1234123412341234;
        wr_enable=1;
        #10;
        wr_enable=0;

        wr_addr=5'b01111; //reg 15
        wr_data=64'h5678567856785678;
        wr_enable=1;
        #10;
        wr_enable=0;

        $display("Reading from 2 registers simultaneously \n");
        rd_addr1=5'b01010;
        rd_addr2=5'b01111;
        #10;
        $display("Register 10 (supposed to be 1234123412341234): 0x%h \n",rd_data1);
        $display("Register 15 (supposed to be 5678567856785678): 0x%h \n",rd_data2);

        $display("Let us try to write without write enable being 1 \n");
        wr_addr=5'b1;
        wr_data=64'h1111111111111111;
        wr_enable=0;
        #10;
        rd_addr1=5'b1;
        #10;
        $display("Register 1 value: 0x%h (supposed to be 0) \n",rd_data1);
        $display("Test completed\n");
        $finish;
    end
endmodule

src/wave.vcd
$date
	Wed May 28 11:56:26 2025
$end
$version
	Icarus Verilog
$end
$timescale
	1s
$end
$scope module tb_reg_file $end
$var wire 64 ! rd_data2 [63:0] $end
$var wire 64 " rd_data1 [63:0] $end
$var wire 64 # debug_output [63:0] $end
$var reg 1 $ clk $end
$var reg 5 % rd_addr1 [4:0] $end
$var reg 5 & rd_addr2 [4:0] $end
$var reg 1 ' rst $end
$var reg 5 ( wr_addr [4:0] $end
$var reg 64 ) wr_data [63:0] $end
$var reg 1 * wr_enable $end
$scope module dut $end
$var wire 1 $ clk $end
$var wire 64 + debug_output [63:0] $end
$var wire 5 , rd_addr1 [4:0] $end
$var wire 5 - rd_addr2 [4:0] $end
$var wire 64 . rd_data1 [63:0] $end
$var wire 64 / rd_data2 [63:0] $end
$var wire 1 ' rst $end
$var wire 5 0 wr_addr [4:0] $end
$var wire 64 1 wr_data [63:0] $end
$var wire 1 * wr_enable $end
$scope begin $ivl_for_loop0 $end
$var integer 32 2 i [31:0] $end
$upscope $end
$upscope $end
$upscope $end
$enddefinitions $end
$comment Show the parameter values. $end
$dumpall
$end
#0
$dumpvars
b100000 2
b0 1
b0 0
b0 /
b0 .
b0 -
b0 ,
b0 +
0*
b0 )
b0 (
1'
b0 &
b0 %
0$
b0 #
b0 "
b0 !
$end
#5
b100000 2
1$
#10
0$
#15
b100000 2
1$
#20
0$
0'
#25
1$
#30
0$
b1 &
b1 -
#35
1$
#40
0$
1*
b100100011010001010110011110001001101010111100110111101111 )
b100100011010001010110011110001001101010111100110111101111 1
b101 (
b101 0
#45
1$
#50
0$
b100100011010001010110011110001001101010111100110111101111 "
b100100011010001010110011110001001101010111100110111101111 .
b101 %
b101 ,
0*
#55
1$
#60
0$
1*
b1001000110100000100100011010000010010001101000001001000110100 )
b1001000110100000100100011010000010010001101000001001000110100 1
b1010 (
b1010 0
#65
1$
#70
0$
b101011001111000010101100111100001010110011110000101011001111000 )
b101011001111000010101100111100001010110011110000101011001111000 1
b1111 (
b1111 0
1*
#75
1$
#80
0$
b101011001111000010101100111100001010110011110000101011001111000 !
b101011001111000010101100111100001010110011110000101011001111000 /
b1111 &
b1111 -
b1001000110100000100100011010000010010001101000001001000110100 "
b1001000110100000100100011010000010010001101000001001000110100 .
b1010 %
b1010 ,
0*
#85
1$
#90
0$
b1000100010001000100010001000100010001000100010001000100010001 )
b1000100010001000100010001000100010001000100010001000100010001 1
b1 (
b1 0
#95
1$
#100
0$
b0 "
b0 .
b1 %
b1 ,
